{"index":{"_type":"lib-data","_index":"lib-index"}}
{"taggroup":"index10","datagroup":[{"record":35,"data":"(ionio)ionioa10002161"}],"value":"(ionio)ionioa10002161"}
{"index":{"_type":"lib-data","_index":"lib-index"}}
{"taggroup":"index100","datagroup":[{"record":100,"data":"20050519cgrey0103    ba"}],"value":"20050519cgrey0103    ba"}
{"index":{"_type":"lib-data","_index":"lib-index"}}
{"taggroup":"index200","datagroup":[{"record":200,"data":"GRANT DUFF"}],"value":"GRANT DUFF"}
{"index":{"_type":"lib-data","_index":"lib-index"}}
{"taggroup":"index200","datagroup":[{"record":200,"data":"Shiela"}],"value":"Shiela"}
{"index":{"_type":"lib-data","_index":"lib-index"}}
{"taggroup":"index200","datagroup":[{"record":200,"data":"1913-"}],"value":"1913-"}
{"index":{"_type":"lib-data","_index":"lib-index"}}
{"taggroup":"index800","datagroup":[{"record":856,"data":"http://viaf.org/viaf/115859233"}],"value":"http://viaf.org/viaf/115859233"}
{"index":{"_type":"lib-data","_index":"lib-index"}}
{"taggroup":"index800","datagroup":[{"record":856,"data":"viaf"}],"value":"viaf"}
{"index":{"_type":"lib-data","_index":"lib-index"}}
{"taggroup":"index800","datagroup":[{"record":856,"data":"http://id.loc.gov/authorities/names/n83064573"}],"value":"http://id.loc.gov/authorities/names/n83064573"}
{"index":{"_type":"lib-data","_index":"lib-index"}}
{"taggroup":"index800","datagroup":[{"record":856,"data":"lcna"}],"value":"lcna"}
{"index":{"_type":"lib-data","_index":"lib-index"}}
{"taggroup":"index10","datagroup":[{"record":35,"data":"(ionio)ionioa10002183"}],"value":"(ionio)ionioa10002183"}
{"index":{"_type":"lib-data","_index":"lib-index"}}
{"taggroup":"index100","datagroup":[{"record":100,"data":"20050519cgrey0103    ba"}],"value":"20050519cgrey0103    ba"}
{"index":{"_type":"lib-data","_index":"lib-index"}}
{"taggroup":"index200","datagroup":[{"record":200,"data":"SMITH"}],"value":"SMITH"}
{"index":{"_type":"lib-data","_index":"lib-index"}}
{"taggroup":"index200","datagroup":[{"record":200,"data":"F.Joseph"}],"value":"F.Joseph"}
{"index":{"_type":"lib-data","_index":"lib-index"}}
{"taggroup":"index800","datagroup":[{"record":856,"data":"http://viaf.org/viaf/43216873"}],"value":"http://viaf.org/viaf/43216873"}
{"index":{"_type":"lib-data","_index":"lib-index"}}
{"taggroup":"index800","datagroup":[{"record":856,"data":"viaf"}],"value":"viaf"}
{"index":{"_type":"lib-data","_index":"lib-index"}}
{"taggroup":"index800","datagroup":[{"record":856,"data":"http://id.loc.gov/authorities/names/n83153176"}],"value":"http://id.loc.gov/authorities/names/n83153176"}
{"index":{"_type":"lib-data","_index":"lib-index"}}
{"taggroup":"index800","datagroup":[{"record":856,"data":"lcna"}],"value":"lcna"}
{"index":{"_type":"lib-data","_index":"lib-index"}}
{"taggroup":"index10","datagroup":[{"record":35,"data":"(ionio)ionioa10002501"}],"value":"(ionio)ionioa10002501"}
{"index":{"_type":"lib-data","_index":"lib-index"}}
{"taggroup":"index100","datagroup":[{"record":100,"data":"20050519cgrey0103    ba"}],"value":"20050519cgrey0103    ba"}
{"index":{"_type":"lib-data","_index":"lib-index"}}
{"taggroup":"index200","datagroup":[{"record":200,"data":"Aretino"}],"value":"Aretino"}
{"index":{"_type":"lib-data","_index":"lib-index"}}
{"taggroup":"index200","datagroup":[{"record":200,"data":"Pietro"}],"value":"Pietro"}
{"index":{"_type":"lib-data","_index":"lib-index"}}
{"taggroup":"index200","datagroup":[{"record":200,"data":"1492-1556"}],"value":"1492-1556"}
{"index":{"_type":"lib-data","_index":"lib-index"}}
{"taggroup":"index800","datagroup":[{"record":856,"data":"http://viaf.org/viaf/66609417"}],"value":"http://viaf.org/viaf/66609417"}
{"index":{"_type":"lib-data","_index":"lib-index"}}
{"taggroup":"index800","datagroup":[{"record":856,"data":"viaf"}],"value":"viaf"}
{"index":{"_type":"lib-data","_index":"lib-index"}}
{"taggroup":"index800","datagroup":[{"record":856,"data":"http://id.loc.gov/authorities/names/n79089193"}],"value":"http://id.loc.gov/authorities/names/n79089193"}
{"index":{"_type":"lib-data","_index":"lib-index"}}
{"taggroup":"index800","datagroup":[{"record":856,"data":"lcna"}],"value":"lcna"}
{"index":{"_type":"lib-data","_index":"lib-index"}}
{"taggroup":"index10","datagroup":[{"record":35,"data":"(ionio)ionioa10002984"}],"value":"(ionio)ionioa10002984"}
{"index":{"_type":"lib-data","_index":"lib-index"}}
{"taggroup":"index100","datagroup":[{"record":100,"data":"20050519cgrey0103    ba"}],"value":"20050519cgrey0103    ba"}
{"index":{"_type":"lib-data","_index":"lib-index"}}
{"taggroup":"index200","datagroup":[{"record":200,"data":"Eppstein"}],"value":"Eppstein"}
{"index":{"_type":"lib-data","_index":"lib-index"}}
{"taggroup":"index200","datagroup":[{"record":200,"data":"Ury"}],"value":"Ury"}
{"index":{"_type":"lib-data","_index":"lib-index"}}
{"taggroup":"index200","datagroup":[{"record":200,"data":"1925-"}],"value":"1925-"}
{"index":{"_type":"lib-data","_index":"lib-index"}}
{"taggroup":"index800","datagroup":[{"record":856,"data":"http://viaf.org/viaf/26297752"}],"value":"http://viaf.org/viaf/26297752"}
{"index":{"_type":"lib-data","_index":"lib-index"}}
{"taggroup":"index800","datagroup":[{"record":856,"data":"viaf"}],"value":"viaf"}
{"index":{"_type":"lib-data","_index":"lib-index"}}
{"taggroup":"index800","datagroup":[{"record":856,"data":"http://id.loc.gov/authorities/names/n94093446"}],"value":"http://id.loc.gov/authorities/names/n94093446"}
{"index":{"_type":"lib-data","_index":"lib-index"}}
{"taggroup":"index800","datagroup":[{"record":856,"data":"lcna"}],"value":"lcna"}
{"index":{"_type":"lib-data","_index":"lib-index"}}
{"taggroup":"index10","datagroup":[{"record":35,"data":"(ionio)ionioa10002987"}],"value":"(ionio)ionioa10002987"}
{"index":{"_type":"lib-data","_index":"lib-index"}}
{"taggroup":"index100","datagroup":[{"record":100,"data":"20050519cgrey0103    ba"}],"value":"20050519cgrey0103    ba"}
{"index":{"_type":"lib-data","_index":"lib-index"}}
{"taggroup":"index200","datagroup":[{"record":200,"data":"NEIBAUER"}],"value":"NEIBAUER"}
{"index":{"_type":"lib-data","_index":"lib-index"}}
{"taggroup":"index200","datagroup":[{"record":200,"data":"Alan R."}],"value":"Alan R."}
{"index":{"_type":"lib-data","_index":"lib-index"}}
{"taggroup":"index800","datagroup":[{"record":856,"data":"http://viaf.org/viaf/37895"}],"value":"http://viaf.org/viaf/37895"}
{"index":{"_type":"lib-data","_index":"lib-index"}}
{"taggroup":"index800","datagroup":[{"record":856,"data":"viaf"}],"value":"viaf"}
{"index":{"_type":"lib-data","_index":"lib-index"}}
{"taggroup":"index800","datagroup":[{"record":856,"data":"http://id.loc.gov/authorities/names/n86013887"}],"value":"http://id.loc.gov/authorities/names/n86013887"}
{"index":{"_type":"lib-data","_index":"lib-index"}}
{"taggroup":"index800","datagroup":[{"record":856,"data":"lcna"}],"value":"lcna"}
{"index":{"_type":"lib-data","_index":"lib-index"}}
{"taggroup":"index10","datagroup":[{"record":35,"data":"(ionio)ionioa10001828"}],"value":"(ionio)ionioa10001828"}
{"index":{"_type":"lib-data","_index":"lib-index"}}
{"taggroup":"index100","datagroup":[{"record":100,"data":"20050519cgrey0103    ba"}],"value":"20050519cgrey0103    ba"}
{"index":{"_type":"lib-data","_index":"lib-index"}}
{"taggroup":"index200","datagroup":[{"record":200,"data":"WEBER"}],"value":"WEBER"}
{"index":{"_type":"lib-data","_index":"lib-index"}}
{"taggroup":"index200","datagroup":[{"record":200,"data":"Edith"}],"value":"Edith"}
{"index":{"_type":"lib-data","_index":"lib-index"}}
{"taggroup":"index800","datagroup":[{"record":856,"data":"http://viaf.org/viaf/72227794"}],"value":"http://viaf.org/viaf/72227794"}
{"index":{"_type":"lib-data","_index":"lib-index"}}
{"taggroup":"index800","datagroup":[{"record":856,"data":"viaf"}],"value":"viaf"}
{"index":{"_type":"lib-data","_index":"lib-index"}}
{"taggroup":"index800","datagroup":[{"record":856,"data":"http://id.loc.gov/authorities/names/n50020913"}],"value":"http://id.loc.gov/authorities/names/n50020913"}
{"index":{"_type":"lib-data","_index":"lib-index"}}
{"taggroup":"index800","datagroup":[{"record":856,"data":"lcna"}],"value":"lcna"}
{"index":{"_type":"lib-data","_index":"lib-index"}}
{"taggroup":"index10","datagroup":[{"record":35,"data":"(ionio)ionioa10003031"}],"value":"(ionio)ionioa10003031"}
{"index":{"_type":"lib-data","_index":"lib-index"}}
{"taggroup":"index100","datagroup":[{"record":100,"data":"20050519cgrey0103    ba"}],"value":"20050519cgrey0103    ba"}
{"index":{"_type":"lib-data","_index":"lib-index"}}
{"taggroup":"index200","datagroup":[{"record":200,"data":"ROBERTSON"}],"value":"ROBERTSON"}
{"index":{"_type":"lib-data","_index":"lib-index"}}
{"taggroup":"index200","datagroup":[{"record":200,"data":"David"}],"value":"David"}
{"index":{"_type":"lib-data","_index":"lib-index"}}
{"taggroup":"index800","datagroup":[{"record":856,"data":"http://viaf.org/viaf/304990846"}],"value":"http://viaf.org/viaf/304990846"}
{"index":{"_type":"lib-data","_index":"lib-index"}}
{"taggroup":"index800","datagroup":[{"record":856,"data":"viaf"}],"value":"viaf"}
{"index":{"_type":"lib-data","_index":"lib-index"}}
{"taggroup":"index800","datagroup":[{"record":856,"data":"http://id.loc.gov/authorities/names/n84155420"}],"value":"http://id.loc.gov/authorities/names/n84155420"}
{"index":{"_type":"lib-data","_index":"lib-index"}}
{"taggroup":"index800","datagroup":[{"record":856,"data":"lcna"}],"value":"lcna"}
{"index":{"_type":"lib-data","_index":"lib-index"}}
{"taggroup":"index10","datagroup":[{"record":35,"data":"(ionio)ionioa10003037"}],"value":"(ionio)ionioa10003037"}
{"index":{"_type":"lib-data","_index":"lib-index"}}
{"taggroup":"index100","datagroup":[{"record":100,"data":"20050519cgrey0103    ba"}],"value":"20050519cgrey0103    ba"}
{"index":{"_type":"lib-data","_index":"lib-index"}}
{"taggroup":"index200","datagroup":[{"record":200,"data":"REUCHLIN"}],"value":"REUCHLIN"}
{"index":{"_type":"lib-data","_index":"lib-index"}}
{"taggroup":"index200","datagroup":[{"record":200,"data":"Maurice"}],"value":"Maurice"}
{"index":{"_type":"lib-data","_index":"lib-index"}}
{"taggroup":"index800","datagroup":[{"record":856,"data":"http://viaf.org/viaf/108852345"}],"value":"http://viaf.org/viaf/108852345"}
{"index":{"_type":"lib-data","_index":"lib-index"}}
{"taggroup":"index800","datagroup":[{"record":856,"data":"viaf"}],"value":"viaf"}
{"index":{"_type":"lib-data","_index":"lib-index"}}
{"taggroup":"index800","datagroup":[{"record":856,"data":"http://id.loc.gov/authorities/names/n50045211"}],"value":"http://id.loc.gov/authorities/names/n50045211"}
{"index":{"_type":"lib-data","_index":"lib-index"}}
{"taggroup":"index800","datagroup":[{"record":856,"data":"lcna"}],"value":"lcna"}
{"index":{"_type":"lib-data","_index":"lib-index"}}
{"taggroup":"index10","datagroup":[{"record":35,"data":"(ionio)ionioa10000721"}],"value":"(ionio)ionioa10000721"}
{"index":{"_type":"lib-data","_index":"lib-index"}}
{"taggroup":"index100","datagroup":[{"record":100,"data":"20131126agrey010303  ba"}],"value":"20131126agrey010303  ba"}
{"index":{"_type":"lib-data","_index":"lib-index"}}
{"taggroup":"index100","datagroup":[{"record":101,"data":"fre"}],"value":"fre"}
{"index":{"_type":"lib-data","_index":"lib-index"}}
{"taggroup":"index100","datagroup":[{"record":102,"data":"FR"}],"value":"FR"}
{"index":{"_type":"lib-data","_index":"lib-index"}}
{"taggroup":"index100","datagroup":[{"record":106,"data":"0"}],"value":"0"}
{"index":{"_type":"lib-data","_index":"lib-index"}}
{"taggroup":"index100","datagroup":[{"record":120,"data":"ba"}],"value":"ba"}
{"index":{"_type":"lib-data","_index":"lib-index"}}
{"taggroup":"index100","datagroup":[{"record":152,"data":"AACR2 2nd rev. ed."}],"value":"AACR2 2nd rev. ed."}
{"index":{"_type":"lib-data","_index":"lib-index"}}
{"taggroup":"index100","datagroup":[{"record":152,"data":"lcna"}],"value":"lcna"}
{"index":{"_type":"lib-data","_index":"lib-index"}}
{"taggroup":"index200","datagroup":[{"record":200,"data":"Stendhal"}],"value":"Stendhal"}
{"index":{"_type":"lib-data","_index":"lib-index"}}
{"taggroup":"index200","datagroup":[{"record":200,"data":"1783-1842"}],"value":"1783-1842"}
{"index":{"_type":"lib-data","_index":"lib-index"}}
{"taggroup":"index800","datagroup":[{"record":801,"data":"GR"}],"value":"GR"}
{"index":{"_type":"lib-data","_index":"lib-index"}}
{"taggroup":"index800","datagroup":[{"record":801,"data":"Ionian University"}],"value":"Ionian University"}
{"index":{"_type":"lib-data","_index":"lib-index"}}
{"taggroup":"index800","datagroup":[{"record":801,"data":"20140529"}],"value":"20140529"}
{"index":{"_type":"lib-data","_index":"lib-index"}}
{"taggroup":"index800","datagroup":[{"record":810,"data":"L.C."}],"value":"L.C."}
{"index":{"_type":"lib-data","_index":"lib-index"}}
{"taggroup":"index800","datagroup":[{"record":856,"data":"http://viaf.org/viaf/17823"}],"value":"http://viaf.org/viaf/17823"}
{"index":{"_type":"lib-data","_index":"lib-index"}}
{"taggroup":"index800","datagroup":[{"record":856,"data":"viaf"}],"value":"viaf"}
{"index":{"_type":"lib-data","_index":"lib-index"}}
{"taggroup":"index800","datagroup":[{"record":856,"data":"http://id.loc.gov/authorities/names/n78095494"}],"value":"http://id.loc.gov/authorities/names/n78095494"}
{"index":{"_type":"lib-data","_index":"lib-index"}}
{"taggroup":"index800","datagroup":[{"record":856,"data":"lcna"}],"value":"lcna"}
{"index":{"_type":"lib-data","_index":"lib-index"}}
{"taggroup":"index900","datagroup":[{"record":970,"data":"Aslanidi"}],"value":"Aslanidi"}
{"index":{"_type":"lib-data","_index":"lib-index"}}
{"taggroup":"index900","datagroup":[{"record":970,"data":"2014-05"}],"value":"2014-05"}
{"index":{"_type":"lib-data","_index":"lib-index"}}
{"taggroup":"index10","datagroup":[{"record":35,"data":"(ionio)ionioa10001987"}],"value":"(ionio)ionioa10001987"}
{"index":{"_type":"lib-data","_index":"lib-index"}}
{"taggroup":"index100","datagroup":[{"record":100,"data":"20050519agrey010303  ba"}],"value":"20050519agrey010303  ba"}
{"index":{"_type":"lib-data","_index":"lib-index"}}
{"taggroup":"index100","datagroup":[{"record":106,"data":"0"}],"value":"0"}
{"index":{"_type":"lib-data","_index":"lib-index"}}
{"taggroup":"index100","datagroup":[{"record":120,"data":"ba"}],"value":"ba"}
{"index":{"_type":"lib-data","_index":"lib-index"}}
{"taggroup":"index100","datagroup":[{"record":152,"data":"AACR2 2nd rev. ed."}],"value":"AACR2 2nd rev. ed."}
{"index":{"_type":"lib-data","_index":"lib-index"}}
{"taggroup":"index100","datagroup":[{"record":152,"data":"lcna"}],"value":"lcna"}
{"index":{"_type":"lib-data","_index":"lib-index"}}
{"taggroup":"index200","datagroup":[{"record":200,"data":"Stravinsky"}],"value":"Stravinsky"}
{"index":{"_type":"lib-data","_index":"lib-index"}}
{"taggroup":"index200","datagroup":[{"record":200,"data":"Igor"}],"value":"Igor"}
{"index":{"_type":"lib-data","_index":"lib-index"}}
{"taggroup":"index200","datagroup":[{"record":200,"data":"1882-1971"}],"value":"1882-1971"}
{"index":{"_type":"lib-data","_index":"lib-index"}}
{"taggroup":"index300","datagroup":[{"record":340,"data":"Composer"}],"value":"Composer"}
{"index":{"_type":"lib-data","_index":"lib-index"}}
{"taggroup":"index800","datagroup":[{"record":801,"data":"GR"}],"value":"GR"}
{"index":{"_type":"lib-data","_index":"lib-index"}}
{"taggroup":"index800","datagroup":[{"record":801,"data":"Ionian University"}],"value":"Ionian University"}
{"index":{"_type":"lib-data","_index":"lib-index"}}
{"taggroup":"index800","datagroup":[{"record":801,"data":"20090220"}],"value":"20090220"}
{"index":{"_type":"lib-data","_index":"lib-index"}}
{"taggroup":"index800","datagroup":[{"record":856,"data":"http://viaf.org/viaf/17309155"}],"value":"http://viaf.org/viaf/17309155"}
{"index":{"_type":"lib-data","_index":"lib-index"}}
{"taggroup":"index800","datagroup":[{"record":856,"data":"viaf"}],"value":"viaf"}
{"index":{"_type":"lib-data","_index":"lib-index"}}
{"taggroup":"index800","datagroup":[{"record":856,"data":"http://id.loc.gov/authorities/names/n79070061"}],"value":"http://id.loc.gov/authorities/names/n79070061"}
{"index":{"_type":"lib-data","_index":"lib-index"}}
{"taggroup":"index800","datagroup":[{"record":856,"data":"lcna"}],"value":"lcna"}
{"index":{"_type":"lib-data","_index":"lib-index"}}
{"taggroup":"index900","datagroup":[{"record":970,"data":"Aslanidi"}],"value":"Aslanidi"}
{"index":{"_type":"lib-data","_index":"lib-index"}}
{"taggroup":"index900","datagroup":[{"record":970,"data":"2014-01"}],"value":"2014-01"}
{"index":{"_type":"lib-data","_index":"lib-index"}}
{"taggroup":"index10","datagroup":[{"record":35,"data":"(ionio)ionioa10001988"}],"value":"(ionio)ionioa10001988"}
{"index":{"_type":"lib-data","_index":"lib-index"}}
{"taggroup":"index100","datagroup":[{"record":100,"data":"20050519cgrey0103    ba"}],"value":"20050519cgrey0103    ba"}
{"index":{"_type":"lib-data","_index":"lib-index"}}
{"taggroup":"index200","datagroup":[{"record":200,"data":"RAHBARI"}],"value":"RAHBARI"}
{"index":{"_type":"lib-data","_index":"lib-index"}}
{"taggroup":"index200","datagroup":[{"record":200,"data":"Alexander"}],"value":"Alexander"}
{"index":{"_type":"lib-data","_index":"lib-index"}}
{"taggroup":"index200","datagroup":[{"record":200,"data":"1948-"}],"value":"1948-"}
{"index":{"_type":"lib-data","_index":"lib-index"}}
{"taggroup":"index800","datagroup":[{"record":856,"data":"http://viaf.org/viaf/61737848"}],"value":"http://viaf.org/viaf/61737848"}
{"index":{"_type":"lib-data","_index":"lib-index"}}
{"taggroup":"index800","datagroup":[{"record":856,"data":"viaf"}],"value":"viaf"}
{"index":{"_type":"lib-data","_index":"lib-index"}}
{"taggroup":"index800","datagroup":[{"record":856,"data":"http://id.loc.gov/authorities/names/nr94014400"}],"value":"http://id.loc.gov/authorities/names/nr94014400"}
{"index":{"_type":"lib-data","_index":"lib-index"}}
{"taggroup":"index800","datagroup":[{"record":856,"data":"lcna"}],"value":"lcna"}
{"index":{"_type":"lib-data","_index":"lib-index"}}
{"taggroup":"index10","datagroup":[{"record":35,"data":"(ionio)ionioa10004559"}],"value":"(ionio)ionioa10004559"}
{"index":{"_type":"lib-data","_index":"lib-index"}}
{"taggroup":"index10","datagroup":[{"record":35,"data":"(ionio)ionioa10001459"}],"value":"(ionio)ionioa10001459"}
{"index":{"_type":"lib-data","_index":"lib-index"}}
{"taggroup":"index100","datagroup":[{"record":100,"data":"20050519agrey010303  ba"}],"value":"20050519agrey010303  ba"}
{"index":{"_type":"lib-data","_index":"lib-index"}}
{"taggroup":"index100","datagroup":[{"record":101,"data":"eng"}],"value":"eng"}
{"index":{"_type":"lib-data","_index":"lib-index"}}
{"taggroup":"index100","datagroup":[{"record":102,"data":"US"}],"value":"US"}
{"index":{"_type":"lib-data","_index":"lib-index"}}
{"taggroup":"index100","datagroup":[{"record":106,"data":"0"}],"value":"0"}
{"index":{"_type":"lib-data","_index":"lib-index"}}
{"taggroup":"index100","datagroup":[{"record":120,"data":"ba"}],"value":"ba"}
{"index":{"_type":"lib-data","_index":"lib-index"}}
{"taggroup":"index100","datagroup":[{"record":152,"data":"AACR2 2nd rev. ed."}],"value":"AACR2 2nd rev. ed."}
{"index":{"_type":"lib-data","_index":"lib-index"}}
{"taggroup":"index100","datagroup":[{"record":152,"data":"lcna"}],"value":"lcna"}
{"index":{"_type":"lib-data","_index":"lib-index"}}
{"taggroup":"index200","datagroup":[{"record":200,"data":"Gershwin"}],"value":"Gershwin"}
{"index":{"_type":"lib-data","_index":"lib-index"}}
{"taggroup":"index200","datagroup":[{"record":200,"data":"George"}],"value":"George"}
{"index":{"_type":"lib-data","_index":"lib-index"}}
{"taggroup":"index200","datagroup":[{"record":200,"data":"1898-1937"}],"value":"1898-1937"}
{"index":{"_type":"lib-data","_index":"lib-index"}}
{"taggroup":"index800","datagroup":[{"record":801,"data":"GR"}],"value":"GR"}
{"index":{"_type":"lib-data","_index":"lib-index"}}
{"taggroup":"index800","datagroup":[{"record":801,"data":"Ionian University"}],"value":"Ionian University"}
{"index":{"_type":"lib-data","_index":"lib-index"}}
{"taggroup":"index800","datagroup":[{"record":801,"data":"20100303"}],"value":"20100303"}
{"index":{"_type":"lib-data","_index":"lib-index"}}
{"taggroup":"index800","datagroup":[{"record":810,"data":"L.C."}],"value":"L.C."}
{"index":{"_type":"lib-data","_index":"lib-index"}}
{"taggroup":"index800","datagroup":[{"record":856,"data":"http://viaf.org/viaf/61554329"}],"value":"http://viaf.org/viaf/61554329"}
{"index":{"_type":"lib-data","_index":"lib-index"}}
{"taggroup":"index800","datagroup":[{"record":856,"data":"viaf"}],"value":"viaf"}
{"index":{"_type":"lib-data","_index":"lib-index"}}
{"taggroup":"index800","datagroup":[{"record":856,"data":"http://id.loc.gov/authorities/names/n79077265"}],"value":"http://id.loc.gov/authorities/names/n79077265"}
{"index":{"_type":"lib-data","_index":"lib-index"}}
{"taggroup":"index800","datagroup":[{"record":856,"data":"lcna"}],"value":"lcna"}
{"index":{"_type":"lib-data","_index":"lib-index"}}
{"taggroup":"index900","datagroup":[{"record":970,"data":"Aslanidi"}],"value":"Aslanidi"}
{"index":{"_type":"lib-data","_index":"lib-index"}}
{"taggroup":"index900","datagroup":[{"record":970,"data":"2014-04"}],"value":"2014-04"}
{"index":{"_type":"lib-data","_index":"lib-index"}}
{"taggroup":"index10","datagroup":[{"record":35,"data":"(ionio)ionioa10001856"}],"value":"(ionio)ionioa10001856"}
{"index":{"_type":"lib-data","_index":"lib-index"}}
{"taggroup":"index100","datagroup":[{"record":100,"data":"20050519cgrey0103    ba"}],"value":"20050519cgrey0103    ba"}
{"index":{"_type":"lib-data","_index":"lib-index"}}
{"taggroup":"index200","datagroup":[{"record":200,"data":"GYORY"}],"value":"GYORY"}
{"index":{"_type":"lib-data","_index":"lib-index"}}
{"taggroup":"index200","datagroup":[{"record":200,"data":"Jean"}],"value":"Jean"}
{"index":{"_type":"lib-data","_index":"lib-index"}}
{"taggroup":"index800","datagroup":[{"record":856,"data":"http://viaf.org/viaf/15213547"}],"value":"http://viaf.org/viaf/15213547"}
{"index":{"_type":"lib-data","_index":"lib-index"}}
{"taggroup":"index800","datagroup":[{"record":856,"data":"viaf"}],"value":"viaf"}
{"index":{"_type":"lib-data","_index":"lib-index"}}
{"taggroup":"index800","datagroup":[{"record":856,"data":"http://id.loc.gov/authorities/names/n91065357"}],"value":"http://id.loc.gov/authorities/names/n91065357"}
{"index":{"_type":"lib-data","_index":"lib-index"}}
{"taggroup":"index800","datagroup":[{"record":856,"data":"lcna"}],"value":"lcna"}
{"index":{"_type":"lib-data","_index":"lib-index"}}
{"taggroup":"index10","datagroup":[{"record":35,"data":"(ionio)ionioa10001677"}],"value":"(ionio)ionioa10001677"}
{"index":{"_type":"lib-data","_index":"lib-index"}}
{"taggroup":"index100","datagroup":[{"record":100,"data":"20050519cgrey0103    ba"}],"value":"20050519cgrey0103    ba"}
{"index":{"_type":"lib-data","_index":"lib-index"}}
{"taggroup":"index200","datagroup":[{"record":200,"data":"Hild"}],"value":"Hild"}
{"index":{"_type":"lib-data","_index":"lib-index"}}
{"taggroup":"index200","datagroup":[{"record":200,"data":"Friedrich"}],"value":"Friedrich"}
{"index":{"_type":"lib-data","_index":"lib-index"}}
{"taggroup":"index800","datagroup":[{"record":856,"data":"http://viaf.org/viaf/147485808"}],"value":"http://viaf.org/viaf/147485808"}
{"index":{"_type":"lib-data","_index":"lib-index"}}
{"taggroup":"index800","datagroup":[{"record":856,"data":"viaf"}],"value":"viaf"}
{"index":{"_type":"lib-data","_index":"lib-index"}}
{"taggroup":"index800","datagroup":[{"record":856,"data":"http://id.loc.gov/authorities/names/nb2005013710"}],"value":"http://id.loc.gov/authorities/names/nb2005013710"}
{"index":{"_type":"lib-data","_index":"lib-index"}}
{"taggroup":"index800","datagroup":[{"record":856,"data":"lcna"}],"value":"lcna"}
{"index":{"_type":"lib-data","_index":"lib-index"}}
{"taggroup":"index10","datagroup":[{"record":35,"data":"(ionio)ionioa10001676"}],"value":"(ionio)ionioa10001676"}
{"index":{"_type":"lib-data","_index":"lib-index"}}
{"taggroup":"index100","datagroup":[{"record":100,"data":"20050519cgrey0103    ba"}],"value":"20050519cgrey0103    ba"}
{"index":{"_type":"lib-data","_index":"lib-index"}}
{"taggroup":"index200","datagroup":[{"record":200,"data":"Koder"}],"value":"Koder"}
{"index":{"_type":"lib-data","_index":"lib-index"}}
{"taggroup":"index200","datagroup":[{"record":200,"data":"Johannes"}],"value":"Johannes"}
{"index":{"_type":"lib-data","_index":"lib-index"}}
{"taggroup":"index800","datagroup":[{"record":856,"data":"http://viaf.org/viaf/25795558"}],"value":"http://viaf.org/viaf/25795558"}
{"index":{"_type":"lib-data","_index":"lib-index"}}
{"taggroup":"index800","datagroup":[{"record":856,"data":"viaf"}],"value":"viaf"}
{"index":{"_type":"lib-data","_index":"lib-index"}}
{"taggroup":"index800","datagroup":[{"record":856,"data":"http://id.loc.gov/authorities/names/n80156039"}],"value":"http://id.loc.gov/authorities/names/n80156039"}
{"index":{"_type":"lib-data","_index":"lib-index"}}
{"taggroup":"index800","datagroup":[{"record":856,"data":"lcna"}],"value":"lcna"}
{"index":{"_type":"lib-data","_index":"lib-index"}}
{"taggroup":"index10","datagroup":[{"record":35,"data":"(ionio)ionioa10001670"}],"value":"(ionio)ionioa10001670"}
{"index":{"_type":"lib-data","_index":"lib-index"}}
{"taggroup":"index100","datagroup":[{"record":100,"data":"20050519cgrey0103    ba"}],"value":"20050519cgrey0103    ba"}
{"index":{"_type":"lib-data","_index":"lib-index"}}
{"taggroup":"index200","datagroup":[{"record":200,"data":"Etienne"}],"value":"Etienne"}
{"index":{"_type":"lib-data","_index":"lib-index"}}
{"taggroup":"index200","datagroup":[{"record":200,"data":"Robert"}],"value":"Robert"}
{"index":{"_type":"lib-data","_index":"lib-index"}}
{"taggroup":"index800","datagroup":[{"record":856,"data":"http://viaf.org/viaf/111567113"}],"value":"http://viaf.org/viaf/111567113"}
{"index":{"_type":"lib-data","_index":"lib-index"}}
{"taggroup":"index800","datagroup":[{"record":856,"data":"viaf"}],"value":"viaf"}
{"index":{"_type":"lib-data","_index":"lib-index"}}
{"taggroup":"index800","datagroup":[{"record":856,"data":"http://id.loc.gov/authorities/names/n84186414"}],"value":"http://id.loc.gov/authorities/names/n84186414"}
{"index":{"_type":"lib-data","_index":"lib-index"}}
{"taggroup":"index800","datagroup":[{"record":856,"data":"lcna"}],"value":"lcna"}
{"index":{"_type":"lib-data","_index":"lib-index"}}
{"taggroup":"index10","datagroup":[{"record":35,"data":"(ionio)ionioa10003013"}],"value":"(ionio)ionioa10003013"}
{"index":{"_type":"lib-data","_index":"lib-index"}}
{"taggroup":"index100","datagroup":[{"record":100,"data":"20050519cgrey0103    ba"}],"value":"20050519cgrey0103    ba"}
{"index":{"_type":"lib-data","_index":"lib-index"}}
{"taggroup":"index200","datagroup":[{"record":200,"data":"KOCH"}],"value":"KOCH"}
{"index":{"_type":"lib-data","_index":"lib-index"}}
{"taggroup":"index200","datagroup":[{"record":200,"data":"Heinrich Christoph"}],"value":"Heinrich Christoph"}
{"index":{"_type":"lib-data","_index":"lib-index"}}
{"taggroup":"index200","datagroup":[{"record":200,"data":"1749-1816"}],"value":"1749-1816"}
{"index":{"_type":"lib-data","_index":"lib-index"}}
{"taggroup":"index800","datagroup":[{"record":856,"data":"http://viaf.org/viaf/9985355"}],"value":"http://viaf.org/viaf/9985355"}
{"index":{"_type":"lib-data","_index":"lib-index"}}
{"taggroup":"index800","datagroup":[{"record":856,"data":"viaf"}],"value":"viaf"}
{"index":{"_type":"lib-data","_index":"lib-index"}}
{"taggroup":"index800","datagroup":[{"record":856,"data":"http://id.loc.gov/authorities/names/n82165268"}],"value":"http://id.loc.gov/authorities/names/n82165268"}
{"index":{"_type":"lib-data","_index":"lib-index"}}
{"taggroup":"index800","datagroup":[{"record":856,"data":"lcna"}],"value":"lcna"}
{"index":{"_type":"lib-data","_index":"lib-index"}}
{"taggroup":"index10","datagroup":[{"record":35,"data":"(ionio)ionioa10002170"}],"value":"(ionio)ionioa10002170"}
{"index":{"_type":"lib-data","_index":"lib-index"}}
{"taggroup":"index100","datagroup":[{"record":100,"data":"20050519cgrey0103    ba"}],"value":"20050519cgrey0103    ba"}
{"index":{"_type":"lib-data","_index":"lib-index"}}
{"taggroup":"index200","datagroup":[{"record":200,"data":"WESSON"}],"value":"WESSON"}
{"index":{"_type":"lib-data","_index":"lib-index"}}
{"taggroup":"index200","datagroup":[{"record":200,"data":"Caren"}],"value":"Caren"}
{"index":{"_type":"lib-data","_index":"lib-index"}}
{"taggroup":"index800","datagroup":[{"record":856,"data":"http://viaf.org/viaf/51829278"}],"value":"http://viaf.org/viaf/51829278"}
{"index":{"_type":"lib-data","_index":"lib-index"}}
{"taggroup":"index800","datagroup":[{"record":856,"data":"viaf"}],"value":"viaf"}
{"index":{"_type":"lib-data","_index":"lib-index"}}
{"taggroup":"index800","datagroup":[{"record":856,"data":"http://id.loc.gov/authorities/names/n83169601"}],"value":"http://id.loc.gov/authorities/names/n83169601"}
{"index":{"_type":"lib-data","_index":"lib-index"}}
{"taggroup":"index800","datagroup":[{"record":856,"data":"lcna"}],"value":"lcna"}
{"index":{"_type":"lib-data","_index":"lib-index"}}
{"taggroup":"index10","datagroup":[{"record":35,"data":"(ionio)ionioa10002516"}],"value":"(ionio)ionioa10002516"}
{"index":{"_type":"lib-data","_index":"lib-index"}}
{"taggroup":"index100","datagroup":[{"record":100,"data":"20050519cgrey0103    ba"}],"value":"20050519cgrey0103    ba"}
{"index":{"_type":"lib-data","_index":"lib-index"}}
{"taggroup":"index200","datagroup":[{"record":200,"data":"KRAUSE"}],"value":"KRAUSE"}
{"index":{"_type":"lib-data","_index":"lib-index"}}
{"taggroup":"index200","datagroup":[{"record":200,"data":"Keith"}],"value":"Keith"}
{"index":{"_type":"lib-data","_index":"lib-index"}}
{"taggroup":"index800","datagroup":[{"record":856,"data":"http://viaf.org/viaf/64069345"}],"value":"http://viaf.org/viaf/64069345"}
{"index":{"_type":"lib-data","_index":"lib-index"}}
{"taggroup":"index800","datagroup":[{"record":856,"data":"viaf"}],"value":"viaf"}
{"index":{"_type":"lib-data","_index":"lib-index"}}
{"taggroup":"index800","datagroup":[{"record":856,"data":"http://id.loc.gov/authorities/names/n91076035"}],"value":"http://id.loc.gov/authorities/names/n91076035"}
{"index":{"_type":"lib-data","_index":"lib-index"}}
{"taggroup":"index800","datagroup":[{"record":856,"data":"lcna"}],"value":"lcna"}
{"index":{"_type":"lib-data","_index":"lib-index"}}
{"taggroup":"index10","datagroup":[{"record":35,"data":"(ionio)ionioa10002518"}],"value":"(ionio)ionioa10002518"}
{"index":{"_type":"lib-data","_index":"lib-index"}}
{"taggroup":"index100","datagroup":[{"record":100,"data":"20050519cgrey0103    ba"}],"value":"20050519cgrey0103    ba"}
{"index":{"_type":"lib-data","_index":"lib-index"}}
{"taggroup":"index200","datagroup":[{"record":200,"data":"Boniface"}],"value":"Boniface"}
{"index":{"_type":"lib-data","_index":"lib-index"}}
{"taggroup":"index200","datagroup":[{"record":200,"data":"Priscilla"}],"value":"Priscilla"}
{"index":{"_type":"lib-data","_index":"lib-index"}}
{"taggroup":"index800","datagroup":[{"record":856,"data":"http://viaf.org/viaf/48131872"}],"value":"http://viaf.org/viaf/48131872"}
{"index":{"_type":"lib-data","_index":"lib-index"}}
{"taggroup":"index800","datagroup":[{"record":856,"data":"viaf"}],"value":"viaf"}
{"index":{"_type":"lib-data","_index":"lib-index"}}
{"taggroup":"index800","datagroup":[{"record":856,"data":"http://id.loc.gov/authorities/names/n83010785"}],"value":"http://id.loc.gov/authorities/names/n83010785"}
{"index":{"_type":"lib-data","_index":"lib-index"}}
{"taggroup":"index800","datagroup":[{"record":856,"data":"lcna"}],"value":"lcna"}
{"index":{"_type":"lib-data","_index":"lib-index"}}
{"taggroup":"index10","datagroup":[{"record":35,"data":"(ionio)ionioa10002993"}],"value":"(ionio)ionioa10002993"}
{"index":{"_type":"lib-data","_index":"lib-index"}}
{"taggroup":"index100","datagroup":[{"record":100,"data":"20050519agrey010301  ba"}],"value":"20050519agrey010301  ba"}
{"index":{"_type":"lib-data","_index":"lib-index"}}
{"taggroup":"index100","datagroup":[{"record":101,"data":"ger"}],"value":"ger"}
{"index":{"_type":"lib-data","_index":"lib-index"}}
{"taggroup":"index100","datagroup":[{"record":102,"data":"DE"}],"value":"DE"}
{"index":{"_type":"lib-data","_index":"lib-index"}}
{"taggroup":"index100","datagroup":[{"record":106,"data":"0"}],"value":"0"}
{"index":{"_type":"lib-data","_index":"lib-index"}}
{"taggroup":"index100","datagroup":[{"record":120,"data":"ba"}],"value":"ba"}
{"index":{"_type":"lib-data","_index":"lib-index"}}
{"taggroup":"index100","datagroup":[{"record":152,"data":"AACR2 2nd rev. ed."}],"value":"AACR2 2nd rev. ed."}
{"index":{"_type":"lib-data","_index":"lib-index"}}
{"taggroup":"index100","datagroup":[{"record":152,"data":"lcna"}],"value":"lcna"}
{"index":{"_type":"lib-data","_index":"lib-index"}}
{"taggroup":"index200","datagroup":[{"record":200,"data":"Bach"}],"value":"Bach"}
{"index":{"_type":"lib-data","_index":"lib-index"}}
{"taggroup":"index200","datagroup":[{"record":200,"data":"Johann Sebastian"}],"value":"Johann Sebastian"}
{"index":{"_type":"lib-data","_index":"lib-index"}}
{"taggroup":"index200","datagroup":[{"record":200,"data":"1685-1750"}],"value":"1685-1750"}
{"index":{"_type":"lib-data","_index":"lib-index"}}
{"taggroup":"index400","datagroup":[{"record":400,"data":"Bach"}],"value":"Bach"}
{"index":{"_type":"lib-data","_index":"lib-index"}}
{"taggroup":"index400","datagroup":[{"record":400,"data":"J. S."}],"value":"J. S."}
{"index":{"_type":"lib-data","_index":"lib-index"}}
{"taggroup":"index400","datagroup":[{"record":400,"data":"1685-1750"}],"value":"1685-1750"}
{"index":{"_type":"lib-data","_index":"lib-index"}}
{"taggroup":"index400","datagroup":[{"record":400,"data":"Bach"}],"value":"Bach"}
{"index":{"_type":"lib-data","_index":"lib-index"}}
{"taggroup":"index400","datagroup":[{"record":400,"data":"Gio. Seb."}],"value":"Gio. Seb."}
{"index":{"_type":"lib-data","_index":"lib-index"}}
{"taggroup":"index400","datagroup":[{"record":400,"data":"1685-1750"}],"value":"1685-1750"}
{"index":{"_type":"lib-data","_index":"lib-index"}}
{"taggroup":"index400","datagroup":[{"record":400,"data":"Bach"}],"value":"Bach"}
{"index":{"_type":"lib-data","_index":"lib-index"}}
{"taggroup":"index400","datagroup":[{"record":400,"data":"G. S."}],"value":"G. S."}
{"index":{"_type":"lib-data","_index":"lib-index"}}
{"taggroup":"index400","datagroup":[{"record":400,"data":"1685-1750"}],"value":"1685-1750"}
{"index":{"_type":"lib-data","_index":"lib-index"}}
{"taggroup":"index400","datagroup":[{"record":400,"data":"Μπαχ"}],"value":"Μπαχ"}
{"index":{"_type":"lib-data","_index":"lib-index"}}
{"taggroup":"index400","datagroup":[{"record":400,"data":"1685-1750"}],"value":"1685-1750"}
{"index":{"_type":"lib-data","_index":"lib-index"}}
{"taggroup":"index800","datagroup":[{"record":801,"data":"GR"}],"value":"GR"}
{"index":{"_type":"lib-data","_index":"lib-index"}}
{"taggroup":"index800","datagroup":[{"record":801,"data":"Ionian University"}],"value":"Ionian University"}
{"index":{"_type":"lib-data","_index":"lib-index"}}
{"taggroup":"index800","datagroup":[{"record":801,"data":"20090514"}],"value":"20090514"}
{"index":{"_type":"lib-data","_index":"lib-index"}}
{"taggroup":"index800","datagroup":[{"record":810,"data":"Air on a G string, c1994"}],"value":"Air on a G string, c1994"}
{"index":{"_type":"lib-data","_index":"lib-index"}}
{"taggroup":"index800","datagroup":[{"record":810,"data":"t.p. (J. S. Bach)"}],"value":"t.p. (J. S. Bach)"}
{"index":{"_type":"lib-data","_index":"lib-index"}}
{"taggroup":"index800","datagroup":[{"record":810,"data":"Composizioni, [18--]"}],"value":"Composizioni, [18--]"}
{"index":{"_type":"lib-data","_index":"lib-index"}}
{"taggroup":"index800","datagroup":[{"record":810,"data":"t.p. (Gio. Seb. Bach)"}],"value":"t.p. (Gio. Seb. Bach)"}
{"index":{"_type":"lib-data","_index":"lib-index"}}
{"taggroup":"index800","datagroup":[{"record":810,"data":"Il clavicembalo bem temperato, 1946"}],"value":"Il clavicembalo bem temperato, 1946"}
{"index":{"_type":"lib-data","_index":"lib-index"}}
{"taggroup":"index800","datagroup":[{"record":810,"data":"t.p. (G. S. Bach)"}],"value":"t.p. (G. S. Bach)"}
{"index":{"_type":"lib-data","_index":"lib-index"}}
{"taggroup":"index800","datagroup":[{"record":810,"data":"Μπαχ [SR] 2001"}],"value":"Μπαχ [SR] 2001"}
{"index":{"_type":"lib-data","_index":"lib-index"}}
{"taggroup":"index800","datagroup":[{"record":810,"data":"L.C."}],"value":"L.C."}
{"index":{"_type":"lib-data","_index":"lib-index"}}
{"taggroup":"index800","datagroup":[{"record":856,"data":"http://viaf.org/viaf/12304462"}],"value":"http://viaf.org/viaf/12304462"}
{"index":{"_type":"lib-data","_index":"lib-index"}}
{"taggroup":"index800","datagroup":[{"record":856,"data":"viaf"}],"value":"viaf"}
{"index":{"_type":"lib-data","_index":"lib-index"}}
{"taggroup":"index800","datagroup":[{"record":856,"data":"http://id.loc.gov/authorities/names/n79021425"}],"value":"http://id.loc.gov/authorities/names/n79021425"}
{"index":{"_type":"lib-data","_index":"lib-index"}}
{"taggroup":"index800","datagroup":[{"record":856,"data":"lcna"}],"value":"lcna"}
{"index":{"_type":"lib-data","_index":"lib-index"}}
{"taggroup":"index900","datagroup":[{"record":970,"data":"Aslanidi"}],"value":"Aslanidi"}
{"index":{"_type":"lib-data","_index":"lib-index"}}
{"taggroup":"index900","datagroup":[{"record":970,"data":"2009-09"}],"value":"2009-09"}
{"index":{"_type":"lib-data","_index":"lib-index"}}
{"taggroup":"index10","datagroup":[{"record":35,"data":"(ionio)ionioa10002994"}],"value":"(ionio)ionioa10002994"}
{"index":{"_type":"lib-data","_index":"lib-index"}}
{"taggroup":"index100","datagroup":[{"record":100,"data":"20050519cgrey0103    ba"}],"value":"20050519cgrey0103    ba"}
{"index":{"_type":"lib-data","_index":"lib-index"}}
{"taggroup":"index200","datagroup":[{"record":200,"data":"HENDRICKS"}],"value":"HENDRICKS"}
{"index":{"_type":"lib-data","_index":"lib-index"}}
{"taggroup":"index200","datagroup":[{"record":200,"data":"Chris"}],"value":"Chris"}
{"index":{"_type":"lib-data","_index":"lib-index"}}
{"taggroup":"index800","datagroup":[{"record":856,"data":"http://viaf.org/viaf/76154136"}],"value":"http://viaf.org/viaf/76154136"}
{"index":{"_type":"lib-data","_index":"lib-index"}}
{"taggroup":"index800","datagroup":[{"record":856,"data":"viaf"}],"value":"viaf"}
{"index":{"_type":"lib-data","_index":"lib-index"}}
{"taggroup":"index800","datagroup":[{"record":856,"data":"http://id.loc.gov/authorities/names/nr00018297"}],"value":"http://id.loc.gov/authorities/names/nr00018297"}
{"index":{"_type":"lib-data","_index":"lib-index"}}
{"taggroup":"index800","datagroup":[{"record":856,"data":"lcna"}],"value":"lcna"}
{"index":{"_type":"lib-data","_index":"lib-index"}}
{"taggroup":"index10","datagroup":[{"record":35,"data":"(ionio)ionioa10087125"}],"value":"(ionio)ionioa10087125"}
{"index":{"_type":"lib-data","_index":"lib-index"}}
{"taggroup":"index10","datagroup":[{"record":35,"data":"(ionio)ionioa10003002"}],"value":"(ionio)ionioa10003002"}
{"index":{"_type":"lib-data","_index":"lib-index"}}
{"taggroup":"index100","datagroup":[{"record":100,"data":"20050519cgrey0103    ba"}],"value":"20050519cgrey0103    ba"}
{"index":{"_type":"lib-data","_index":"lib-index"}}
{"taggroup":"index200","datagroup":[{"record":200,"data":"HITLER"}],"value":"HITLER"}
{"index":{"_type":"lib-data","_index":"lib-index"}}
{"taggroup":"index200","datagroup":[{"record":200,"data":"Adolf"}],"value":"Adolf"}
{"index":{"_type":"lib-data","_index":"lib-index"}}
{"taggroup":"index200","datagroup":[{"record":200,"data":"1889-1945"}],"value":"1889-1945"}
{"index":{"_type":"lib-data","_index":"lib-index"}}
{"taggroup":"index800","datagroup":[{"record":856,"data":"http://viaf.org/viaf/38190770"}],"value":"http://viaf.org/viaf/38190770"}
{"index":{"_type":"lib-data","_index":"lib-index"}}
{"taggroup":"index800","datagroup":[{"record":856,"data":"viaf"}],"value":"viaf"}
{"index":{"_type":"lib-data","_index":"lib-index"}}
{"taggroup":"index800","datagroup":[{"record":856,"data":"http://id.loc.gov/authorities/names/n79046200"}],"value":"http://id.loc.gov/authorities/names/n79046200"}
{"index":{"_type":"lib-data","_index":"lib-index"}}
{"taggroup":"index800","datagroup":[{"record":856,"data":"lcna"}],"value":"lcna"}
{"index":{"_type":"lib-data","_index":"lib-index"}}
{"taggroup":"index10","datagroup":[{"record":35,"data":"(ionio)ionioa10001467"}],"value":"(ionio)ionioa10001467"}
{"index":{"_type":"lib-data","_index":"lib-index"}}
{"taggroup":"index100","datagroup":[{"record":100,"data":"20050519cgrey0103    ba"}],"value":"20050519cgrey0103    ba"}
{"index":{"_type":"lib-data","_index":"lib-index"}}
{"taggroup":"index200","datagroup":[{"record":200,"data":"KNOWLES"}],"value":"KNOWLES"}
{"index":{"_type":"lib-data","_index":"lib-index"}}
{"taggroup":"index200","datagroup":[{"record":200,"data":"Christine"}],"value":"Christine"}
{"index":{"_type":"lib-data","_index":"lib-index"}}
{"taggroup":"index800","datagroup":[{"record":856,"data":"http://viaf.org/viaf/235333474"}],"value":"http://viaf.org/viaf/235333474"}
{"index":{"_type":"lib-data","_index":"lib-index"}}
{"taggroup":"index800","datagroup":[{"record":856,"data":"viaf"}],"value":"viaf"}
{"index":{"_type":"lib-data","_index":"lib-index"}}
{"taggroup":"index800","datagroup":[{"record":856,"data":"http://id.loc.gov/authorities/names/n84094767"}],"value":"http://id.loc.gov/authorities/names/n84094767"}
{"index":{"_type":"lib-data","_index":"lib-index"}}
{"taggroup":"index800","datagroup":[{"record":856,"data":"lcna"}],"value":"lcna"}
{"index":{"_type":"lib-data","_index":"lib-index"}}
{"taggroup":"index10","datagroup":[{"record":35,"data":"(ionio)ionioa10000438"}],"value":"(ionio)ionioa10000438"}
{"index":{"_type":"lib-data","_index":"lib-index"}}
{"taggroup":"index10","datagroup":[{"record":35,"data":"(ionio)ionioa10000440"}],"value":"(ionio)ionioa10000440"}
{"index":{"_type":"lib-data","_index":"lib-index"}}
{"taggroup":"index100","datagroup":[{"record":100,"data":"20120307agrey010303  ba"}],"value":"20120307agrey010303  ba"}
{"index":{"_type":"lib-data","_index":"lib-index"}}
{"taggroup":"index100","datagroup":[{"record":101,"data":"heb"}],"value":"heb"}
{"index":{"_type":"lib-data","_index":"lib-index"}}
{"taggroup":"index100","datagroup":[{"record":102,"data":"ES"}],"value":"ES"}
{"index":{"_type":"lib-data","_index":"lib-index"}}
{"taggroup":"index100","datagroup":[{"record":106,"data":"0"}],"value":"0"}
{"index":{"_type":"lib-data","_index":"lib-index"}}
{"taggroup":"index100","datagroup":[{"record":120,"data":"ba"}],"value":"ba"}
{"index":{"_type":"lib-data","_index":"lib-index"}}
{"taggroup":"index100","datagroup":[{"record":152,"data":"AACR2 2nd rev. ed."}],"value":"AACR2 2nd rev. ed."}
{"index":{"_type":"lib-data","_index":"lib-index"}}
{"taggroup":"index100","datagroup":[{"record":152,"data":"lcna"}],"value":"lcna"}
{"index":{"_type":"lib-data","_index":"lib-index"}}
{"taggroup":"index200","datagroup":[{"record":200,"data":"Benjamin"}],"value":"Benjamin"}
{"index":{"_type":"lib-data","_index":"lib-index"}}
{"taggroup":"index200","datagroup":[{"record":200,"data":"of Tudela"}],"value":"of Tudela"}
{"index":{"_type":"lib-data","_index":"lib-index"}}
{"taggroup":"index200","datagroup":[{"record":200,"data":"active 12th century"}],"value":"active 12th century"}
{"index":{"_type":"lib-data","_index":"lib-index"}}
{"taggroup":"index400","datagroup":[{"record":400,"data":"Βενιαμίν"}],"value":"Βενιαμίν"}
{"index":{"_type":"lib-data","_index":"lib-index"}}
{"taggroup":"index400","datagroup":[{"record":400,"data":"εκ Τουδέλης"}],"value":"εκ Τουδέλης"}
{"index":{"_type":"lib-data","_index":"lib-index"}}
{"taggroup":"index400","datagroup":[{"record":400,"data":"12ος αιώνας"}],"value":"12ος αιώνας"}
{"index":{"_type":"lib-data","_index":"lib-index"}}
{"taggroup":"index800","datagroup":[{"record":801,"data":"GR"}],"value":"GR"}
{"index":{"_type":"lib-data","_index":"lib-index"}}
{"taggroup":"index800","datagroup":[{"record":801,"data":"Ionian University"}],"value":"Ionian University"}
{"index":{"_type":"lib-data","_index":"lib-index"}}
{"taggroup":"index800","datagroup":[{"record":801,"data":"20120307"}],"value":"20120307"}
{"index":{"_type":"lib-data","_index":"lib-index"}}
{"taggroup":"index800","datagroup":[{"record":810,"data":"Work cat.: Benjamin of Tudela, Το βιβλίο των ταξιδιών, 1994"}],"value":"Work cat.: Benjamin of Tudela, Το βιβλίο των ταξιδιών, 1994"}
{"index":{"_type":"lib-data","_index":"lib-index"}}
{"taggroup":"index800","datagroup":[{"record":810,"data":"Το βιβλίο των ταξιδιών, 1994"}],"value":"Το βιβλίο των ταξιδιών, 1994"}
{"index":{"_type":"lib-data","_index":"lib-index"}}
{"taggroup":"index800","datagroup":[{"record":810,"data":"σ.τ. (Βενιαμίν εκ Τουδέλης)"}],"value":"σ.τ. (Βενιαμίν εκ Τουδέλης)"}
{"index":{"_type":"lib-data","_index":"lib-index"}}
{"taggroup":"index800","datagroup":[{"record":856,"data":"http://viaf.org/viaf/32154389"}],"value":"http://viaf.org/viaf/32154389"}
{"index":{"_type":"lib-data","_index":"lib-index"}}
{"taggroup":"index800","datagroup":[{"record":856,"data":"viaf"}],"value":"viaf"}
{"index":{"_type":"lib-data","_index":"lib-index"}}
{"taggroup":"index800","datagroup":[{"record":856,"data":"http://id.loc.gov/authorities/names/n80065940"}],"value":"http://id.loc.gov/authorities/names/n80065940"}
{"index":{"_type":"lib-data","_index":"lib-index"}}
{"taggroup":"index800","datagroup":[{"record":856,"data":"lcna"}],"value":"lcna"}
{"index":{"_type":"lib-data","_index":"lib-index"}}
{"taggroup":"index900","datagroup":[{"record":970,"data":"Aslanidi"}],"value":"Aslanidi"}
{"index":{"_type":"lib-data","_index":"lib-index"}}
{"taggroup":"index900","datagroup":[{"record":970,"data":"2012-03"}],"value":"2012-03"}
{"index":{"_type":"lib-data","_index":"lib-index"}}
{"taggroup":"index10","datagroup":[{"record":35,"data":"(ionio)ionioa10001865"}],"value":"(ionio)ionioa10001865"}
{"index":{"_type":"lib-data","_index":"lib-index"}}
{"taggroup":"index100","datagroup":[{"record":100,"data":"20050519cgrey010303  ba"}],"value":"20050519cgrey010303  ba"}
{"index":{"_type":"lib-data","_index":"lib-index"}}
{"taggroup":"index200","datagroup":[{"record":200,"data":"Fiedler"}],"value":"Fiedler"}
{"index":{"_type":"lib-data","_index":"lib-index"}}
{"taggroup":"index200","datagroup":[{"record":200,"data":"Maggi"}],"value":"Maggi"}
{"index":{"_type":"lib-data","_index":"lib-index"}}
{"taggroup":"index800","datagroup":[{"record":856,"data":"http://viaf.org/viaf/58993209"}],"value":"http://viaf.org/viaf/58993209"}
{"index":{"_type":"lib-data","_index":"lib-index"}}
{"taggroup":"index800","datagroup":[{"record":856,"data":"viaf"}],"value":"viaf"}
{"index":{"_type":"lib-data","_index":"lib-index"}}
{"taggroup":"index800","datagroup":[{"record":856,"data":"http://id.loc.gov/authorities/names/nr98011814"}],"value":"http://id.loc.gov/authorities/names/nr98011814"}
{"index":{"_type":"lib-data","_index":"lib-index"}}
{"taggroup":"index800","datagroup":[{"record":856,"data":"lcna"}],"value":"lcna"}
{"index":{"_type":"lib-data","_index":"lib-index"}}
{"taggroup":"index10","datagroup":[{"record":35,"data":"(ionio)ionioa10001869"}],"value":"(ionio)ionioa10001869"}
{"index":{"_type":"lib-data","_index":"lib-index"}}
{"taggroup":"index100","datagroup":[{"record":100,"data":"20050519cgrey0103    ba"}],"value":"20050519cgrey0103    ba"}
{"index":{"_type":"lib-data","_index":"lib-index"}}
{"taggroup":"index200","datagroup":[{"record":200,"data":"LOUSSOUARN"}],"value":"LOUSSOUARN"}
{"index":{"_type":"lib-data","_index":"lib-index"}}
{"taggroup":"index200","datagroup":[{"record":200,"data":"Yvon"}],"value":"Yvon"}
{"index":{"_type":"lib-data","_index":"lib-index"}}
{"taggroup":"index800","datagroup":[{"record":856,"data":"http://viaf.org/viaf/17226069"}],"value":"http://viaf.org/viaf/17226069"}
{"index":{"_type":"lib-data","_index":"lib-index"}}
{"taggroup":"index800","datagroup":[{"record":856,"data":"viaf"}],"value":"viaf"}
{"index":{"_type":"lib-data","_index":"lib-index"}}
{"taggroup":"index800","datagroup":[{"record":856,"data":"http://id.loc.gov/authorities/names/n80166966"}],"value":"http://id.loc.gov/authorities/names/n80166966"}
{"index":{"_type":"lib-data","_index":"lib-index"}}
{"taggroup":"index800","datagroup":[{"record":856,"data":"lcna"}],"value":"lcna"}
{"index":{"_type":"lib-data","_index":"lib-index"}}
{"taggroup":"index10","datagroup":[{"record":35,"data":"(ionio)ionioa10001644"}],"value":"(ionio)ionioa10001644"}
{"index":{"_type":"lib-data","_index":"lib-index"}}
{"taggroup":"index100","datagroup":[{"record":100,"data":"20050519agrey010305  ga"}],"value":"20050519agrey010305  ga"}
{"index":{"_type":"lib-data","_index":"lib-index"}}
{"taggroup":"index100","datagroup":[{"record":152,"data":"AACR2 2nd rev. ed."}],"value":"AACR2 2nd rev. ed."}
{"index":{"_type":"lib-data","_index":"lib-index"}}
{"taggroup":"index200","datagroup":[{"record":200,"data":"Πλάτων"}],"value":"Πλάτων"}
{"index":{"_type":"lib-data","_index":"lib-index"}}
{"taggroup":"index200","datagroup":[{"record":200,"data":"427-347 π.Χ."}],"value":"427-347 π.Χ."}
{"index":{"_type":"lib-data","_index":"lib-index"}}
{"taggroup":"index400","datagroup":[{"record":400,"data":"Πλατωνική φιλοσοφία"}],"value":"Πλατωνική φιλοσοφία"}
{"index":{"_type":"lib-data","_index":"lib-index"}}
{"taggroup":"index400","datagroup":[{"record":400,"data":"Πλατωνισμός , Αρχαίος"}],"value":"Πλατωνισμός , Αρχαίος"}
{"index":{"_type":"lib-data","_index":"lib-index"}}
{"taggroup":"index400","datagroup":[{"record":400,"data":"Plato"}],"value":"Plato"}
{"index":{"_type":"lib-data","_index":"lib-index"}}
{"taggroup":"index400","datagroup":[{"record":400,"data":"Platon"}],"value":"Platon"}
{"index":{"_type":"lib-data","_index":"lib-index"}}
{"taggroup":"index600","datagroup":[{"record":676,"data":"184"}],"value":"184"}
{"index":{"_type":"lib-data","_index":"lib-index"}}
{"taggroup":"index600","datagroup":[{"record":676,"data":"Platonic philosophy"}],"value":"Platonic philosophy"}
{"index":{"_type":"lib-data","_index":"lib-index"}}
{"taggroup":"index600","datagroup":[{"record":676,"data":"23η έκδ."}],"value":"23η έκδ."}
{"index":{"_type":"lib-data","_index":"lib-index"}}
{"taggroup":"index700","datagroup":[{"record":700,"data":"Plato"}],"value":"Plato"}
{"index":{"_type":"lib-data","_index":"lib-index"}}
{"taggroup":"index700","datagroup":[{"record":700,"data":"lcna"}],"value":"lcna"}
{"index":{"_type":"lib-data","_index":"lib-index"}}
{"taggroup":"index700","datagroup":[{"record":700,"data":"http://id.loc.gov/authorities/names/n79139459"}],"value":"http://id.loc.gov/authorities/names/n79139459"}
{"index":{"_type":"lib-data","_index":"lib-index"}}
{"taggroup":"index800","datagroup":[{"record":801,"data":"GR"}],"value":"GR"}
{"index":{"_type":"lib-data","_index":"lib-index"}}
{"taggroup":"index800","datagroup":[{"record":801,"data":"Ionian University"}],"value":"Ionian University"}
{"index":{"_type":"lib-data","_index":"lib-index"}}
{"taggroup":"index800","datagroup":[{"record":801,"data":"20100614"}],"value":"20100614"}
{"index":{"_type":"lib-data","_index":"lib-index"}}
{"taggroup":"index800","datagroup":[{"record":810,"data":"Republic, 1993"}],"value":"Republic, 1993"}
{"index":{"_type":"lib-data","_index":"lib-index"}}
{"taggroup":"index800","datagroup":[{"record":810,"data":"t.p. (Plato)"}],"value":"t.p. (Plato)"}
{"index":{"_type":"lib-data","_index":"lib-index"}}
{"taggroup":"index800","datagroup":[{"record":810,"data":"Oeuvres completes, 1997-"}],"value":"Oeuvres completes, 1997-"}
{"index":{"_type":"lib-data","_index":"lib-index"}}
{"taggroup":"index800","datagroup":[{"record":810,"data":"t.p. (Platon)"}],"value":"t.p. (Platon)"}
{"index":{"_type":"lib-data","_index":"lib-index"}}
{"taggroup":"index800","datagroup":[{"record":810,"data":"Ε.Β.Ε."}],"value":"Ε.Β.Ε."}
{"index":{"_type":"lib-data","_index":"lib-index"}}
{"taggroup":"index800","datagroup":[{"record":810,"data":"L.C."}],"value":"L.C."}
{"index":{"_type":"lib-data","_index":"lib-index"}}
{"taggroup":"index800","datagroup":[{"record":810,"data":"Παγκόσμιο βιογραφικό λεξικό, 1990-1991"}],"value":"Παγκόσμιο βιογραφικό λεξικό, 1990-1991"}
{"index":{"_type":"lib-data","_index":"lib-index"}}
{"taggroup":"index800","datagroup":[{"record":810,"data":"τ.8 (Πλάτων·  427 - 347 π.Χ., Αθήνα· φιλόσοφος, ο κορυφαίος της ανθρωπότητας)"}],"value":"τ.8 (Πλάτων·  427 - 347 π.Χ., Αθήνα· φιλόσοφος, ο κορυφαίος της ανθρωπότητας)"}
{"index":{"_type":"lib-data","_index":"lib-index"}}
{"taggroup":"index800","datagroup":[{"record":856,"data":"http://viaf.org/viaf/108159964"}],"value":"http://viaf.org/viaf/108159964"}
{"index":{"_type":"lib-data","_index":"lib-index"}}
{"taggroup":"index800","datagroup":[{"record":856,"data":"viaf"}],"value":"viaf"}
{"index":{"_type":"lib-data","_index":"lib-index"}}
{"taggroup":"index900","datagroup":[{"record":970,"data":"Aslanidi"}],"value":"Aslanidi"}
{"index":{"_type":"lib-data","_index":"lib-index"}}
{"taggroup":"index900","datagroup":[{"record":970,"data":"2010-06"}],"value":"2010-06"}
{"index":{"_type":"lib-data","_index":"lib-index"}}
{"taggroup":"index10","datagroup":[{"record":35,"data":"(ionio)ionioa10002345"}],"value":"(ionio)ionioa10002345"}
{"index":{"_type":"lib-data","_index":"lib-index"}}
{"taggroup":"index100","datagroup":[{"record":100,"data":"20050519agrey010303  ba"}],"value":"20050519agrey010303  ba"}
{"index":{"_type":"lib-data","_index":"lib-index"}}
{"taggroup":"index100","datagroup":[{"record":101,"data":"ita"}],"value":"ita"}
{"index":{"_type":"lib-data","_index":"lib-index"}}
{"taggroup":"index100","datagroup":[{"record":102,"data":"IT"}],"value":"IT"}
{"index":{"_type":"lib-data","_index":"lib-index"}}
{"taggroup":"index100","datagroup":[{"record":106,"data":"0"}],"value":"0"}
{"index":{"_type":"lib-data","_index":"lib-index"}}
{"taggroup":"index100","datagroup":[{"record":120,"data":"ba"}],"value":"ba"}
{"index":{"_type":"lib-data","_index":"lib-index"}}
{"taggroup":"index100","datagroup":[{"record":152,"data":"RDA"}],"value":"RDA"}
{"index":{"_type":"lib-data","_index":"lib-index"}}
{"taggroup":"index100","datagroup":[{"record":152,"data":"lcna"}],"value":"lcna"}
{"index":{"_type":"lib-data","_index":"lib-index"}}
{"taggroup":"index200","datagroup":[{"record":200,"data":"Donizetti"}],"value":"Donizetti"}
{"index":{"_type":"lib-data","_index":"lib-index"}}
{"taggroup":"index200","datagroup":[{"record":200,"data":"Gaetano"}],"value":"Gaetano"}
{"index":{"_type":"lib-data","_index":"lib-index"}}
{"taggroup":"index200","datagroup":[{"record":200,"data":"1797-1848"}],"value":"1797-1848"}
{"index":{"_type":"lib-data","_index":"lib-index"}}
{"taggroup":"index300","datagroup":[{"record":340,"data":"Composer"}],"value":"Composer"}
{"index":{"_type":"lib-data","_index":"lib-index"}}
{"taggroup":"index400","datagroup":[{"record":400,"data":"Donizetti"}],"value":"Donizetti"}
{"index":{"_type":"lib-data","_index":"lib-index"}}
{"taggroup":"index400","datagroup":[{"record":400,"data":"G."}],"value":"G."}
{"index":{"_type":"lib-data","_index":"lib-index"}}
{"taggroup":"index400","datagroup":[{"record":400,"data":"1797-1848"}],"value":"1797-1848"}
{"index":{"_type":"lib-data","_index":"lib-index"}}
{"taggroup":"index400","datagroup":[{"record":400,"data":"(Gaetano)"}],"value":"(Gaetano)"}
{"index":{"_type":"lib-data","_index":"lib-index"}}
{"taggroup":"index800","datagroup":[{"record":801,"data":"GR"}],"value":"GR"}
{"index":{"_type":"lib-data","_index":"lib-index"}}
{"taggroup":"index800","datagroup":[{"record":801,"data":"Ionian University"}],"value":"Ionian University"}
{"index":{"_type":"lib-data","_index":"lib-index"}}
{"taggroup":"index800","datagroup":[{"record":801,"data":"20090604"}],"value":"20090604"}
{"index":{"_type":"lib-data","_index":"lib-index"}}
{"taggroup":"index800","datagroup":[{"record":810,"data":"La favorita, 19--"}],"value":"La favorita, 19--"}
{"index":{"_type":"lib-data","_index":"lib-index"}}
{"taggroup":"index800","datagroup":[{"record":810,"data":"t.p. (G. Donizetti)"}],"value":"t.p. (G. Donizetti)"}
{"index":{"_type":"lib-data","_index":"lib-index"}}
{"taggroup":"index800","datagroup":[{"record":810,"data":"L.C."}],"value":"L.C."}
{"index":{"_type":"lib-data","_index":"lib-index"}}
{"taggroup":"index800","datagroup":[{"record":856,"data":"http://viaf.org/viaf/74037336"}],"value":"http://viaf.org/viaf/74037336"}
{"index":{"_type":"lib-data","_index":"lib-index"}}
{"taggroup":"index800","datagroup":[{"record":856,"data":"viaf"}],"value":"viaf"}
{"index":{"_type":"lib-data","_index":"lib-index"}}
{"taggroup":"index800","datagroup":[{"record":856,"data":"http://id.loc.gov/authorities/names/n79132358"}],"value":"http://id.loc.gov/authorities/names/n79132358"}
{"index":{"_type":"lib-data","_index":"lib-index"}}
{"taggroup":"index800","datagroup":[{"record":856,"data":"lcna"}],"value":"lcna"}
{"index":{"_type":"lib-data","_index":"lib-index"}}
{"taggroup":"index900","datagroup":[{"record":970,"data":"Aslanidi"}],"value":"Aslanidi"}
{"index":{"_type":"lib-data","_index":"lib-index"}}
{"taggroup":"index900","datagroup":[{"record":970,"data":"2013-07"}],"value":"2013-07"}
{"index":{"_type":"lib-data","_index":"lib-index"}}
{"taggroup":"index10","datagroup":[{"record":35,"data":"(ionio)ionioa10002340"}],"value":"(ionio)ionioa10002340"}
{"index":{"_type":"lib-data","_index":"lib-index"}}
{"taggroup":"index100","datagroup":[{"record":100,"data":"20050519cgrey0103    ba"}],"value":"20050519cgrey0103    ba"}
{"index":{"_type":"lib-data","_index":"lib-index"}}
{"taggroup":"index200","datagroup":[{"record":200,"data":"MICHEL"}],"value":"MICHEL"}
{"index":{"_type":"lib-data","_index":"lib-index"}}
{"taggroup":"index200","datagroup":[{"record":200,"data":"Pierre"}],"value":"Pierre"}
{"index":{"_type":"lib-data","_index":"lib-index"}}
{"taggroup":"index800","datagroup":[{"record":856,"data":"http://viaf.org/viaf/223629285"}],"value":"http://viaf.org/viaf/223629285"}
{"index":{"_type":"lib-data","_index":"lib-index"}}
{"taggroup":"index800","datagroup":[{"record":856,"data":"viaf"}],"value":"viaf"}
{"index":{"_type":"lib-data","_index":"lib-index"}}
{"taggroup":"index800","datagroup":[{"record":856,"data":"http://id.loc.gov/authorities/names/n94082329"}],"value":"http://id.loc.gov/authorities/names/n94082329"}
{"index":{"_type":"lib-data","_index":"lib-index"}}
{"taggroup":"index800","datagroup":[{"record":856,"data":"lcna"}],"value":"lcna"}
{"index":{"_type":"lib-data","_index":"lib-index"}}
{"taggroup":"index10","datagroup":[{"record":35,"data":"(ionio)ionioa10002529"}],"value":"(ionio)ionioa10002529"}
{"index":{"_type":"lib-data","_index":"lib-index"}}
{"taggroup":"index100","datagroup":[{"record":100,"data":"20050519cgrey0103    ba"}],"value":"20050519cgrey0103    ba"}
{"index":{"_type":"lib-data","_index":"lib-index"}}
{"taggroup":"index200","datagroup":[{"record":200,"data":"FREUND"}],"value":"FREUND"}
{"index":{"_type":"lib-data","_index":"lib-index"}}
{"taggroup":"index200","datagroup":[{"record":200,"data":"Julien"}],"value":"Julien"}
{"index":{"_type":"lib-data","_index":"lib-index"}}
{"taggroup":"index800","datagroup":[{"record":856,"data":"http://viaf.org/viaf/108494825"}],"value":"http://viaf.org/viaf/108494825"}
{"index":{"_type":"lib-data","_index":"lib-index"}}
{"taggroup":"index800","datagroup":[{"record":856,"data":"viaf"}],"value":"viaf"}
{"index":{"_type":"lib-data","_index":"lib-index"}}
{"taggroup":"index800","datagroup":[{"record":856,"data":"http://id.loc.gov/authorities/names/n81010548"}],"value":"http://id.loc.gov/authorities/names/n81010548"}
{"index":{"_type":"lib-data","_index":"lib-index"}}
{"taggroup":"index800","datagroup":[{"record":856,"data":"lcna"}],"value":"lcna"}
{"index":{"_type":"lib-data","_index":"lib-index"}}
{"taggroup":"index10","datagroup":[{"record":35,"data":"(ionio)ionioa10002234"}],"value":"(ionio)ionioa10002234"}
{"index":{"_type":"lib-data","_index":"lib-index"}}
{"taggroup":"index100","datagroup":[{"record":100,"data":"20050519cgrey0103    ba"}],"value":"20050519cgrey0103    ba"}
{"index":{"_type":"lib-data","_index":"lib-index"}}
{"taggroup":"index200","datagroup":[{"record":200,"data":"Braillard"}],"value":"Braillard"}
{"index":{"_type":"lib-data","_index":"lib-index"}}
{"taggroup":"index200","datagroup":[{"record":200,"data":"Philippe"}],"value":"Philippe"}
{"index":{"_type":"lib-data","_index":"lib-index"}}
{"taggroup":"index800","datagroup":[{"record":856,"data":"http://viaf.org/viaf/4927298"}],"value":"http://viaf.org/viaf/4927298"}
{"index":{"_type":"lib-data","_index":"lib-index"}}
{"taggroup":"index800","datagroup":[{"record":856,"data":"viaf"}],"value":"viaf"}
{"index":{"_type":"lib-data","_index":"lib-index"}}
{"taggroup":"index800","datagroup":[{"record":856,"data":"http://id.loc.gov/authorities/names/n82111885"}],"value":"http://id.loc.gov/authorities/names/n82111885"}
{"index":{"_type":"lib-data","_index":"lib-index"}}
{"taggroup":"index800","datagroup":[{"record":856,"data":"lcna"}],"value":"lcna"}
{"index":{"_type":"lib-data","_index":"lib-index"}}
{"taggroup":"index10","datagroup":[{"record":35,"data":"(ionio)ionioa10002235"}],"value":"(ionio)ionioa10002235"}
{"index":{"_type":"lib-data","_index":"lib-index"}}
{"taggroup":"index100","datagroup":[{"record":100,"data":"20050519cgrey0103    ba"}],"value":"20050519cgrey0103    ba"}
{"index":{"_type":"lib-data","_index":"lib-index"}}
{"taggroup":"index200","datagroup":[{"record":200,"data":"SENARCLENS"}],"value":"SENARCLENS"}
{"index":{"_type":"lib-data","_index":"lib-index"}}
{"taggroup":"index200","datagroup":[{"record":200,"data":"Pierre de"}],"value":"Pierre de"}
{"index":{"_type":"lib-data","_index":"lib-index"}}
{"taggroup":"index800","datagroup":[{"record":856,"data":"http://viaf.org/viaf/95159291"}],"value":"http://viaf.org/viaf/95159291"}
{"index":{"_type":"lib-data","_index":"lib-index"}}
{"taggroup":"index800","datagroup":[{"record":856,"data":"viaf"}],"value":"viaf"}
{"index":{"_type":"lib-data","_index":"lib-index"}}
{"taggroup":"index800","datagroup":[{"record":856,"data":"http://id.loc.gov/authorities/names/n85804915"}],"value":"http://id.loc.gov/authorities/names/n85804915"}
{"index":{"_type":"lib-data","_index":"lib-index"}}
{"taggroup":"index800","datagroup":[{"record":856,"data":"lcna"}],"value":"lcna"}
{"index":{"_type":"lib-data","_index":"lib-index"}}
{"taggroup":"index10","datagroup":[{"record":35,"data":"(ionio)ionioa10001870"}],"value":"(ionio)ionioa10001870"}
{"index":{"_type":"lib-data","_index":"lib-index"}}
{"taggroup":"index100","datagroup":[{"record":100,"data":"20050519cgrey0103    ba"}],"value":"20050519cgrey0103    ba"}
{"index":{"_type":"lib-data","_index":"lib-index"}}
{"taggroup":"index200","datagroup":[{"record":200,"data":"Bredin"}],"value":"Bredin"}
{"index":{"_type":"lib-data","_index":"lib-index"}}
{"taggroup":"index200","datagroup":[{"record":200,"data":"Jean-Denis"}],"value":"Jean-Denis"}
{"index":{"_type":"lib-data","_index":"lib-index"}}
{"taggroup":"index800","datagroup":[{"record":856,"data":"http://viaf.org/viaf/8182"}],"value":"http://viaf.org/viaf/8182"}
{"index":{"_type":"lib-data","_index":"lib-index"}}
{"taggroup":"index800","datagroup":[{"record":856,"data":"viaf"}],"value":"viaf"}
{"index":{"_type":"lib-data","_index":"lib-index"}}
{"taggroup":"index800","datagroup":[{"record":856,"data":"http://id.loc.gov/authorities/names/n84083982"}],"value":"http://id.loc.gov/authorities/names/n84083982"}
{"index":{"_type":"lib-data","_index":"lib-index"}}
{"taggroup":"index800","datagroup":[{"record":856,"data":"lcna"}],"value":"lcna"}
{"index":{"_type":"lib-data","_index":"lib-index"}}
{"taggroup":"index10","datagroup":[{"record":35,"data":"(ionio)ionioa10000059"}],"value":"(ionio)ionioa10000059"}
{"index":{"_type":"lib-data","_index":"lib-index"}}
{"taggroup":"index100","datagroup":[{"record":100,"data":"20120427agrey010301  ba"}],"value":"20120427agrey010301  ba"}
{"index":{"_type":"lib-data","_index":"lib-index"}}
{"taggroup":"index200","datagroup":[{"record":200,"data":"Asor Rosa"}],"value":"Asor Rosa"}
{"index":{"_type":"lib-data","_index":"lib-index"}}
{"taggroup":"index200","datagroup":[{"record":200,"data":"Alberto"}],"value":"Alberto"}
{"index":{"_type":"lib-data","_index":"lib-index"}}
{"taggroup":"index400","datagroup":[{"record":400,"data":"Rosa"}],"value":"Rosa"}
{"index":{"_type":"lib-data","_index":"lib-index"}}
{"taggroup":"index400","datagroup":[{"record":400,"data":"Alberto Asor"}],"value":"Alberto Asor"}
{"index":{"_type":"lib-data","_index":"lib-index"}}
{"taggroup":"index800","datagroup":[{"record":856,"data":"http://viaf.org/viaf/4924891"}],"value":"http://viaf.org/viaf/4924891"}
{"index":{"_type":"lib-data","_index":"lib-index"}}
{"taggroup":"index800","datagroup":[{"record":856,"data":"viaf"}],"value":"viaf"}
{"index":{"_type":"lib-data","_index":"lib-index"}}
{"taggroup":"index800","datagroup":[{"record":856,"data":"http://id.loc.gov/authorities/names/n79006391"}],"value":"http://id.loc.gov/authorities/names/n79006391"}
{"index":{"_type":"lib-data","_index":"lib-index"}}
{"taggroup":"index800","datagroup":[{"record":856,"data":"lcna"}],"value":"lcna"}
{"index":{"_type":"lib-data","_index":"lib-index"}}
{"taggroup":"index10","datagroup":[{"record":35,"data":"(ionio)ionioa10000050"}],"value":"(ionio)ionioa10000050"}
{"index":{"_type":"lib-data","_index":"lib-index"}}
{"taggroup":"index100","datagroup":[{"record":100,"data":"20050519xgrey0103    ba"}],"value":"20050519xgrey0103    ba"}
{"index":{"_type":"lib-data","_index":"lib-index"}}
{"taggroup":"index200","datagroup":[{"record":200,"data":"Pablo"}],"value":"Pablo"}
{"index":{"_type":"lib-data","_index":"lib-index"}}
{"taggroup":"index200","datagroup":[{"record":200,"data":"Michel"}],"value":"Michel"}
{"index":{"_type":"lib-data","_index":"lib-index"}}
{"taggroup":"index800","datagroup":[{"record":856,"data":"http://viaf.org/viaf/3762597"}],"value":"http://viaf.org/viaf/3762597"}
{"index":{"_type":"lib-data","_index":"lib-index"}}
{"taggroup":"index800","datagroup":[{"record":856,"data":"viaf"}],"value":"viaf"}
{"index":{"_type":"lib-data","_index":"lib-index"}}
{"taggroup":"index800","datagroup":[{"record":856,"data":"http://id.loc.gov/authorities/names/n79151551"}],"value":"http://id.loc.gov/authorities/names/n79151551"}
{"index":{"_type":"lib-data","_index":"lib-index"}}
{"taggroup":"index800","datagroup":[{"record":856,"data":"lcna"}],"value":"lcna"}
{"index":{"_type":"lib-data","_index":"lib-index"}}
{"taggroup":"index10","datagroup":[{"record":35,"data":"(ionio)ionioa10001657"}],"value":"(ionio)ionioa10001657"}
{"index":{"_type":"lib-data","_index":"lib-index"}}
{"taggroup":"index100","datagroup":[{"record":100,"data":"20050519cgrey010303  ba"}],"value":"20050519cgrey010303  ba"}
{"index":{"_type":"lib-data","_index":"lib-index"}}
{"taggroup":"index200","datagroup":[{"record":200,"data":"Mandeson"}],"value":"Mandeson"}
{"index":{"_type":"lib-data","_index":"lib-index"}}
{"taggroup":"index200","datagroup":[{"record":200,"data":"Arnold"}],"value":"Arnold"}
{"index":{"_type":"lib-data","_index":"lib-index"}}
{"taggroup":"index800","datagroup":[{"record":856,"data":"http://viaf.org/viaf/236696943"}],"value":"http://viaf.org/viaf/236696943"}
{"index":{"_type":"lib-data","_index":"lib-index"}}
{"taggroup":"index800","datagroup":[{"record":856,"data":"viaf"}],"value":"viaf"}
{"index":{"_type":"lib-data","_index":"lib-index"}}
{"taggroup":"index800","datagroup":[{"record":856,"data":"http://id.loc.gov/authorities/names/n85382200"}],"value":"http://id.loc.gov/authorities/names/n85382200"}
{"index":{"_type":"lib-data","_index":"lib-index"}}
{"taggroup":"index800","datagroup":[{"record":856,"data":"lcna"}],"value":"lcna"}
{"index":{"_type":"lib-data","_index":"lib-index"}}
{"taggroup":"index10","datagroup":[{"record":35,"data":"(ionio)ionioa10002351"}],"value":"(ionio)ionioa10002351"}
{"index":{"_type":"lib-data","_index":"lib-index"}}
{"taggroup":"index100","datagroup":[{"record":100,"data":"20050519cgrey0103    ba"}],"value":"20050519cgrey0103    ba"}
{"index":{"_type":"lib-data","_index":"lib-index"}}
{"taggroup":"index200","datagroup":[{"record":200,"data":"LANOUX"}],"value":"LANOUX"}
{"index":{"_type":"lib-data","_index":"lib-index"}}
{"taggroup":"index200","datagroup":[{"record":200,"data":"Armand"}],"value":"Armand"}
{"index":{"_type":"lib-data","_index":"lib-index"}}
{"taggroup":"index800","datagroup":[{"record":856,"data":"http://viaf.org/viaf/109461660"}],"value":"http://viaf.org/viaf/109461660"}
{"index":{"_type":"lib-data","_index":"lib-index"}}
{"taggroup":"index800","datagroup":[{"record":856,"data":"viaf"}],"value":"viaf"}
{"index":{"_type":"lib-data","_index":"lib-index"}}
{"taggroup":"index800","datagroup":[{"record":856,"data":"http://id.loc.gov/authorities/names/n50035994"}],"value":"http://id.loc.gov/authorities/names/n50035994"}
{"index":{"_type":"lib-data","_index":"lib-index"}}
{"taggroup":"index800","datagroup":[{"record":856,"data":"lcna"}],"value":"lcna"}
{"index":{"_type":"lib-data","_index":"lib-index"}}
{"taggroup":"index10","datagroup":[{"record":35,"data":"(ionio)ionioa10002352"}],"value":"(ionio)ionioa10002352"}
{"index":{"_type":"lib-data","_index":"lib-index"}}
{"taggroup":"index100","datagroup":[{"record":100,"data":"20050519cgrey0103    ba"}],"value":"20050519cgrey0103    ba"}
{"index":{"_type":"lib-data","_index":"lib-index"}}
{"taggroup":"index200","datagroup":[{"record":200,"data":"MITTERAND"}],"value":"MITTERAND"}
{"index":{"_type":"lib-data","_index":"lib-index"}}
{"taggroup":"index200","datagroup":[{"record":200,"data":"Henri"}],"value":"Henri"}
{"index":{"_type":"lib-data","_index":"lib-index"}}
{"taggroup":"index800","datagroup":[{"record":856,"data":"http://viaf.org/viaf/14961"}],"value":"http://viaf.org/viaf/14961"}
{"index":{"_type":"lib-data","_index":"lib-index"}}
{"taggroup":"index800","datagroup":[{"record":856,"data":"viaf"}],"value":"viaf"}
{"index":{"_type":"lib-data","_index":"lib-index"}}
{"taggroup":"index800","datagroup":[{"record":856,"data":"http://id.loc.gov/authorities/names/n50000410"}],"value":"http://id.loc.gov/authorities/names/n50000410"}
{"index":{"_type":"lib-data","_index":"lib-index"}}
{"taggroup":"index800","datagroup":[{"record":856,"data":"lcna"}],"value":"lcna"}
{"index":{"_type":"lib-data","_index":"lib-index"}}
{"taggroup":"index10","datagroup":[{"record":35,"data":"(ionio)ionioa10002357"}],"value":"(ionio)ionioa10002357"}
{"index":{"_type":"lib-data","_index":"lib-index"}}
{"taggroup":"index100","datagroup":[{"record":100,"data":"20050519cgrey0103    ba"}],"value":"20050519cgrey0103    ba"}
{"index":{"_type":"lib-data","_index":"lib-index"}}
{"taggroup":"index200","datagroup":[{"record":200,"data":"MURPHY"}],"value":"MURPHY"}
{"index":{"_type":"lib-data","_index":"lib-index"}}
{"taggroup":"index200","datagroup":[{"record":200,"data":"Joseph"}],"value":"Joseph"}
{"index":{"_type":"lib-data","_index":"lib-index"}}
{"taggroup":"index800","datagroup":[{"record":856,"data":"http://viaf.org/viaf/304985191"}],"value":"http://viaf.org/viaf/304985191"}
{"index":{"_type":"lib-data","_index":"lib-index"}}
{"taggroup":"index800","datagroup":[{"record":856,"data":"viaf"}],"value":"viaf"}
{"index":{"_type":"lib-data","_index":"lib-index"}}
{"taggroup":"index800","datagroup":[{"record":856,"data":"http://id.loc.gov/authorities/names/n82112848"}],"value":"http://id.loc.gov/authorities/names/n82112848"}
{"index":{"_type":"lib-data","_index":"lib-index"}}
{"taggroup":"index800","datagroup":[{"record":856,"data":"lcna"}],"value":"lcna"}
{"index":{"_type":"lib-data","_index":"lib-index"}}
{"taggroup":"index10","datagroup":[{"record":35,"data":"(ionio)ionioa10002687"}],"value":"(ionio)ionioa10002687"}
{"index":{"_type":"lib-data","_index":"lib-index"}}
{"taggroup":"index100","datagroup":[{"record":100,"data":"20050519cgrey0103    ba"}],"value":"20050519cgrey0103    ba"}
{"index":{"_type":"lib-data","_index":"lib-index"}}
{"taggroup":"index200","datagroup":[{"record":200,"data":"GOULD"}],"value":"GOULD"}
{"index":{"_type":"lib-data","_index":"lib-index"}}
{"taggroup":"index200","datagroup":[{"record":200,"data":"Stephen Jay"}],"value":"Stephen Jay"}
{"index":{"_type":"lib-data","_index":"lib-index"}}
{"taggroup":"index800","datagroup":[{"record":856,"data":"http://viaf.org/viaf/108205470"}],"value":"http://viaf.org/viaf/108205470"}
{"index":{"_type":"lib-data","_index":"lib-index"}}
{"taggroup":"index800","datagroup":[{"record":856,"data":"viaf"}],"value":"viaf"}
{"index":{"_type":"lib-data","_index":"lib-index"}}
{"taggroup":"index800","datagroup":[{"record":856,"data":"http://id.loc.gov/authorities/names/n79145199"}],"value":"http://id.loc.gov/authorities/names/n79145199"}
{"index":{"_type":"lib-data","_index":"lib-index"}}
{"taggroup":"index800","datagroup":[{"record":856,"data":"lcna"}],"value":"lcna"}
{"index":{"_type":"lib-data","_index":"lib-index"}}
{"taggroup":"index10","datagroup":[{"record":35,"data":"(ionio)ionioa10002686"}],"value":"(ionio)ionioa10002686"}
{"index":{"_type":"lib-data","_index":"lib-index"}}
{"taggroup":"index100","datagroup":[{"record":100,"data":"20050519cgrey010303  ba"}],"value":"20050519cgrey010303  ba"}
{"index":{"_type":"lib-data","_index":"lib-index"}}
{"taggroup":"index200","datagroup":[{"record":200,"data":"Purcell"}],"value":"Purcell"}
{"index":{"_type":"lib-data","_index":"lib-index"}}
{"taggroup":"index200","datagroup":[{"record":200,"data":"Rosamond Wolff"}],"value":"Rosamond Wolff"}
{"index":{"_type":"lib-data","_index":"lib-index"}}
{"taggroup":"index800","datagroup":[{"record":856,"data":"http://viaf.org/viaf/93008584"}],"value":"http://viaf.org/viaf/93008584"}
{"index":{"_type":"lib-data","_index":"lib-index"}}
{"taggroup":"index800","datagroup":[{"record":856,"data":"viaf"}],"value":"viaf"}
{"index":{"_type":"lib-data","_index":"lib-index"}}
{"taggroup":"index800","datagroup":[{"record":856,"data":"http://id.loc.gov/authorities/names/n81062664"}],"value":"http://id.loc.gov/authorities/names/n81062664"}
{"index":{"_type":"lib-data","_index":"lib-index"}}
{"taggroup":"index800","datagroup":[{"record":856,"data":"lcna"}],"value":"lcna"}
{"index":{"_type":"lib-data","_index":"lib-index"}}
{"taggroup":"index10","datagroup":[{"record":35,"data":"(ionio)ionioa10002531"}],"value":"(ionio)ionioa10002531"}
{"index":{"_type":"lib-data","_index":"lib-index"}}
{"taggroup":"index100","datagroup":[{"record":100,"data":"20050519agrey010305  ba"}],"value":"20050519agrey010305  ba"}
{"index":{"_type":"lib-data","_index":"lib-index"}}
{"taggroup":"index100","datagroup":[{"record":101,"data":"ita"}],"value":"ita"}
{"index":{"_type":"lib-data","_index":"lib-index"}}
{"taggroup":"index100","datagroup":[{"record":102,"data":"IT"}],"value":"IT"}
{"index":{"_type":"lib-data","_index":"lib-index"}}
{"taggroup":"index100","datagroup":[{"record":106,"data":"0"}],"value":"0"}
{"index":{"_type":"lib-data","_index":"lib-index"}}
{"taggroup":"index100","datagroup":[{"record":120,"data":"ba"}],"value":"ba"}
{"index":{"_type":"lib-data","_index":"lib-index"}}
{"taggroup":"index100","datagroup":[{"record":152,"data":"AACR2 2nd rev. ed."}],"value":"AACR2 2nd rev. ed."}
{"index":{"_type":"lib-data","_index":"lib-index"}}
{"taggroup":"index100","datagroup":[{"record":152,"data":"lcna"}],"value":"lcna"}
{"index":{"_type":"lib-data","_index":"lib-index"}}
{"taggroup":"index200","datagroup":[{"record":200,"data":"Bellini"}],"value":"Bellini"}
{"index":{"_type":"lib-data","_index":"lib-index"}}
{"taggroup":"index200","datagroup":[{"record":200,"data":"Vincenzo"}],"value":"Vincenzo"}
{"index":{"_type":"lib-data","_index":"lib-index"}}
{"taggroup":"index200","datagroup":[{"record":200,"data":"1801-1835"}],"value":"1801-1835"}
{"index":{"_type":"lib-data","_index":"lib-index"}}
{"taggroup":"index800","datagroup":[{"record":801,"data":"GR"}],"value":"GR"}
{"index":{"_type":"lib-data","_index":"lib-index"}}
{"taggroup":"index800","datagroup":[{"record":801,"data":"Ionian University"}],"value":"Ionian University"}
{"index":{"_type":"lib-data","_index":"lib-index"}}
{"taggroup":"index800","datagroup":[{"record":801,"data":"20100223"}],"value":"20100223"}
{"index":{"_type":"lib-data","_index":"lib-index"}}
{"taggroup":"index800","datagroup":[{"record":810,"data":"L.C."}],"value":"L.C."}
{"index":{"_type":"lib-data","_index":"lib-index"}}
{"taggroup":"index800","datagroup":[{"record":856,"data":"http://viaf.org/viaf/39560983"}],"value":"http://viaf.org/viaf/39560983"}
{"index":{"_type":"lib-data","_index":"lib-index"}}
{"taggroup":"index800","datagroup":[{"record":856,"data":"viaf"}],"value":"viaf"}
{"index":{"_type":"lib-data","_index":"lib-index"}}
{"taggroup":"index800","datagroup":[{"record":856,"data":"http://id.loc.gov/authorities/names/n80122768"}],"value":"http://id.loc.gov/authorities/names/n80122768"}
{"index":{"_type":"lib-data","_index":"lib-index"}}
{"taggroup":"index800","datagroup":[{"record":856,"data":"lcna"}],"value":"lcna"}
{"index":{"_type":"lib-data","_index":"lib-index"}}
{"taggroup":"index900","datagroup":[{"record":970,"data":"Aslanidi"}],"value":"Aslanidi"}
{"index":{"_type":"lib-data","_index":"lib-index"}}
{"taggroup":"index900","datagroup":[{"record":970,"data":"2015-02"}],"value":"2015-02"}
{"index":{"_type":"lib-data","_index":"lib-index"}}
{"taggroup":"index10","datagroup":[{"record":35,"data":"(ionio)ionioa10000974"}],"value":"(ionio)ionioa10000974"}
{"index":{"_type":"lib-data","_index":"lib-index"}}
{"taggroup":"index100","datagroup":[{"record":100,"data":"20130703agrey010305  ba"}],"value":"20130703agrey010305  ba"}
{"index":{"_type":"lib-data","_index":"lib-index"}}
{"taggroup":"index200","datagroup":[{"record":200,"data":"Nostradamus"}],"value":"Nostradamus"}
{"index":{"_type":"lib-data","_index":"lib-index"}}
{"taggroup":"index200","datagroup":[{"record":200,"data":"1503-1566"}],"value":"1503-1566"}
{"index":{"_type":"lib-data","_index":"lib-index"}}
{"taggroup":"index400","datagroup":[{"record":400,"data":"Notredame"}],"value":"Notredame"}
{"index":{"_type":"lib-data","_index":"lib-index"}}
{"taggroup":"index400","datagroup":[{"record":400,"data":"Michel de"}],"value":"Michel de"}
{"index":{"_type":"lib-data","_index":"lib-index"}}
{"taggroup":"index400","datagroup":[{"record":400,"data":"1503-1566"}],"value":"1503-1566"}
{"index":{"_type":"lib-data","_index":"lib-index"}}
{"taggroup":"index400","datagroup":[{"record":400,"data":"Νοστράδαμος"}],"value":"Νοστράδαμος"}
{"index":{"_type":"lib-data","_index":"lib-index"}}
{"taggroup":"index400","datagroup":[{"record":400,"data":"1503-1566"}],"value":"1503-1566"}
{"index":{"_type":"lib-data","_index":"lib-index"}}
{"taggroup":"index800","datagroup":[{"record":856,"data":"http://viaf.org/viaf/16387613"}],"value":"http://viaf.org/viaf/16387613"}
{"index":{"_type":"lib-data","_index":"lib-index"}}
{"taggroup":"index800","datagroup":[{"record":856,"data":"viaf"}],"value":"viaf"}
{"index":{"_type":"lib-data","_index":"lib-index"}}
{"taggroup":"index800","datagroup":[{"record":856,"data":"http://id.loc.gov/authorities/names/n80009809"}],"value":"http://id.loc.gov/authorities/names/n80009809"}
{"index":{"_type":"lib-data","_index":"lib-index"}}
{"taggroup":"index800","datagroup":[{"record":856,"data":"lcna"}],"value":"lcna"}
{"index":{"_type":"lib-data","_index":"lib-index"}}
{"taggroup":"index10","datagroup":[{"record":35,"data":"(ionio)ionioa10003062"}],"value":"(ionio)ionioa10003062"}
{"index":{"_type":"lib-data","_index":"lib-index"}}
{"taggroup":"index100","datagroup":[{"record":100,"data":"20050519cgrey0103    ba"}],"value":"20050519cgrey0103    ba"}
{"index":{"_type":"lib-data","_index":"lib-index"}}
{"taggroup":"index200","datagroup":[{"record":200,"data":"Driessen"}],"value":"Driessen"}
{"index":{"_type":"lib-data","_index":"lib-index"}}
{"taggroup":"index200","datagroup":[{"record":200,"data":"Karen C."}],"value":"Karen C."}
{"index":{"_type":"lib-data","_index":"lib-index"}}
{"taggroup":"index800","datagroup":[{"record":856,"data":"http://viaf.org/viaf/12452133"}],"value":"http://viaf.org/viaf/12452133"}
{"index":{"_type":"lib-data","_index":"lib-index"}}
{"taggroup":"index800","datagroup":[{"record":856,"data":"viaf"}],"value":"viaf"}
{"index":{"_type":"lib-data","_index":"lib-index"}}
{"taggroup":"index800","datagroup":[{"record":856,"data":"http://id.loc.gov/authorities/names/n94038284"}],"value":"http://id.loc.gov/authorities/names/n94038284"}
{"index":{"_type":"lib-data","_index":"lib-index"}}
{"taggroup":"index800","datagroup":[{"record":856,"data":"lcna"}],"value":"lcna"}
{"index":{"_type":"lib-data","_index":"lib-index"}}
{"taggroup":"index10","datagroup":[{"record":35,"data":"(ionio)ionioa10003063"}],"value":"(ionio)ionioa10003063"}
{"index":{"_type":"lib-data","_index":"lib-index"}}
{"taggroup":"index100","datagroup":[{"record":100,"data":"20050519cgrey0103    ba"}],"value":"20050519cgrey0103    ba"}
{"index":{"_type":"lib-data","_index":"lib-index"}}
{"taggroup":"index200","datagroup":[{"record":200,"data":"SMYTH"}],"value":"SMYTH"}
{"index":{"_type":"lib-data","_index":"lib-index"}}
{"taggroup":"index200","datagroup":[{"record":200,"data":"Sheila A."}],"value":"Sheila A."}
{"index":{"_type":"lib-data","_index":"lib-index"}}
{"taggroup":"index800","datagroup":[{"record":856,"data":"http://viaf.org/viaf/2617575"}],"value":"http://viaf.org/viaf/2617575"}
{"index":{"_type":"lib-data","_index":"lib-index"}}
{"taggroup":"index800","datagroup":[{"record":856,"data":"viaf"}],"value":"viaf"}
{"index":{"_type":"lib-data","_index":"lib-index"}}
{"taggroup":"index800","datagroup":[{"record":856,"data":"http://id.loc.gov/authorities/names/n94038285"}],"value":"http://id.loc.gov/authorities/names/n94038285"}
{"index":{"_type":"lib-data","_index":"lib-index"}}
{"taggroup":"index800","datagroup":[{"record":856,"data":"lcna"}],"value":"lcna"}
{"index":{"_type":"lib-data","_index":"lib-index"}}
{"taggroup":"index10","datagroup":[{"record":35,"data":"(ionio)ionioa10002826"}],"value":"(ionio)ionioa10002826"}
{"index":{"_type":"lib-data","_index":"lib-index"}}
{"taggroup":"index100","datagroup":[{"record":100,"data":"20050519cgrey0103    ba"}],"value":"20050519cgrey0103    ba"}
{"index":{"_type":"lib-data","_index":"lib-index"}}
{"taggroup":"index200","datagroup":[{"record":200,"data":"Amin"}],"value":"Amin"}
{"index":{"_type":"lib-data","_index":"lib-index"}}
{"taggroup":"index200","datagroup":[{"record":200,"data":"Samir"}],"value":"Samir"}
{"index":{"_type":"lib-data","_index":"lib-index"}}
{"taggroup":"index800","datagroup":[{"record":856,"data":"http://viaf.org/viaf/108317093"}],"value":"http://viaf.org/viaf/108317093"}
{"index":{"_type":"lib-data","_index":"lib-index"}}
{"taggroup":"index800","datagroup":[{"record":856,"data":"viaf"}],"value":"viaf"}
{"index":{"_type":"lib-data","_index":"lib-index"}}
{"taggroup":"index800","datagroup":[{"record":856,"data":"http://id.loc.gov/authorities/names/n80005668"}],"value":"http://id.loc.gov/authorities/names/n80005668"}
{"index":{"_type":"lib-data","_index":"lib-index"}}
{"taggroup":"index800","datagroup":[{"record":856,"data":"lcna"}],"value":"lcna"}
{"index":{"_type":"lib-data","_index":"lib-index"}}
{"taggroup":"index10","datagroup":[{"record":35,"data":"(ionio)ionioa10001795"}],"value":"(ionio)ionioa10001795"}
{"index":{"_type":"lib-data","_index":"lib-index"}}
{"taggroup":"index100","datagroup":[{"record":100,"data":"20050519cgrey0103    ba"}],"value":"20050519cgrey0103    ba"}
{"index":{"_type":"lib-data","_index":"lib-index"}}
{"taggroup":"index200","datagroup":[{"record":200,"data":"IMBERT"}],"value":"IMBERT"}
{"index":{"_type":"lib-data","_index":"lib-index"}}
{"taggroup":"index200","datagroup":[{"record":200,"data":"Jean"}],"value":"Jean"}
{"index":{"_type":"lib-data","_index":"lib-index"}}
{"taggroup":"index800","datagroup":[{"record":856,"data":"http://viaf.org/viaf/106965799"}],"value":"http://viaf.org/viaf/106965799"}
{"index":{"_type":"lib-data","_index":"lib-index"}}
{"taggroup":"index800","datagroup":[{"record":856,"data":"viaf"}],"value":"viaf"}
{"index":{"_type":"lib-data","_index":"lib-index"}}
{"taggroup":"index800","datagroup":[{"record":856,"data":"http://id.loc.gov/authorities/names/n50031602"}],"value":"http://id.loc.gov/authorities/names/n50031602"}
{"index":{"_type":"lib-data","_index":"lib-index"}}
{"taggroup":"index800","datagroup":[{"record":856,"data":"lcna"}],"value":"lcna"}
{"index":{"_type":"lib-data","_index":"lib-index"}}
{"taggroup":"index10","datagroup":[{"record":35,"data":"(ionio)ionioa10000316"}],"value":"(ionio)ionioa10000316"}
{"index":{"_type":"lib-data","_index":"lib-index"}}
{"taggroup":"index100","datagroup":[{"record":100,"data":"20130920agrey010305  ga"}],"value":"20130920agrey010305  ga"}
{"index":{"_type":"lib-data","_index":"lib-index"}}
{"taggroup":"index200","datagroup":[{"record":200,"data":"Robespierre"}],"value":"Robespierre"}
{"index":{"_type":"lib-data","_index":"lib-index"}}
{"taggroup":"index200","datagroup":[{"record":200,"data":"Maximilien"}],"value":"Maximilien"}
{"index":{"_type":"lib-data","_index":"lib-index"}}
{"taggroup":"index200","datagroup":[{"record":200,"data":"1758-1794"}],"value":"1758-1794"}
{"index":{"_type":"lib-data","_index":"lib-index"}}
{"taggroup":"index400","datagroup":[{"record":400,"data":"Ροβεσπιέρος"}],"value":"Ροβεσπιέρος"}
{"index":{"_type":"lib-data","_index":"lib-index"}}
{"taggroup":"index800","datagroup":[{"record":856,"data":"http://viaf.org/viaf/89401473"}],"value":"http://viaf.org/viaf/89401473"}
{"index":{"_type":"lib-data","_index":"lib-index"}}
{"taggroup":"index800","datagroup":[{"record":856,"data":"viaf"}],"value":"viaf"}
{"index":{"_type":"lib-data","_index":"lib-index"}}
{"taggroup":"index800","datagroup":[{"record":856,"data":"http://id.loc.gov/authorities/names/n50061705"}],"value":"http://id.loc.gov/authorities/names/n50061705"}
{"index":{"_type":"lib-data","_index":"lib-index"}}
{"taggroup":"index800","datagroup":[{"record":856,"data":"lcna"}],"value":"lcna"}
{"index":{"_type":"lib-data","_index":"lib-index"}}
{"taggroup":"index10","datagroup":[{"record":35,"data":"(ionio)ionioa10002792"}],"value":"(ionio)ionioa10002792"}
{"index":{"_type":"lib-data","_index":"lib-index"}}
{"taggroup":"index100","datagroup":[{"record":100,"data":"20050519cgrey0103    ba"}],"value":"20050519cgrey0103    ba"}
{"index":{"_type":"lib-data","_index":"lib-index"}}
{"taggroup":"index200","datagroup":[{"record":200,"data":"MARTIN"}],"value":"MARTIN"}
{"index":{"_type":"lib-data","_index":"lib-index"}}
{"taggroup":"index200","datagroup":[{"record":200,"data":"Ron G."}],"value":"Ron G."}
{"index":{"_type":"lib-data","_index":"lib-index"}}
{"taggroup":"index800","datagroup":[{"record":856,"data":"http://viaf.org/viaf/43493395"}],"value":"http://viaf.org/viaf/43493395"}
{"index":{"_type":"lib-data","_index":"lib-index"}}
{"taggroup":"index800","datagroup":[{"record":856,"data":"viaf"}],"value":"viaf"}
{"index":{"_type":"lib-data","_index":"lib-index"}}
{"taggroup":"index800","datagroup":[{"record":856,"data":"http://id.loc.gov/authorities/names/n92032510"}],"value":"http://id.loc.gov/authorities/names/n92032510"}
{"index":{"_type":"lib-data","_index":"lib-index"}}
{"taggroup":"index800","datagroup":[{"record":856,"data":"lcna"}],"value":"lcna"}
